[{"Name":"Green onions","Type":"Produce","Store":"Metropolitan Market","Expired":false,"PurchaseDate":"2015-07-28T03:16:12.762Z","ExpirationDate":"2017-04-08T23:25:14.798Z","Quantity":1},{"Name":"Watercress","Type":"Produce","Store":"Trader Joe's","Expired":true,"PurchaseDate":"2017-05-03T16:11:15.426Z","ExpirationDate":"2017-01-04T13:06:00.169Z","Quantity":7},{"Name":"Rutabaga","Type":"Produce","Store":"Albertsons","Expired":false,"PurchaseDate":"2016-03-17T01:01:37.729Z","ExpirationDate":"2017-08-18T01:55:17.052Z","Quantity":2},{"Name":"Ice cream","Type":"Dairy","Store":"Safeway","Expired":true,"PurchaseDate":"2018-02-13T11:46:05.283Z","ExpirationDate":"2017-04-02T23:29:54.019Z","Quantity":8},{"Name":"Cabbage","Type":"Produce","Store":"Metropolitan Market","Expired":false,"PurchaseDate":"2016-09-06T18:20:43.39Z","ExpirationDate":"2018-08-23T21:03:15.873Z","Quantity":5},{"Name":"Broccoli","Type":"Produce","Store":"Metropolitan Market","Expired":false,"PurchaseDate":"2017-01-02T05:10:14.32Z","ExpirationDate":"2017-04-25T17:23:05.111Z","Quantity":3},{"Name":"Garlic","Type":"Produce","Store":"Safeway","Expired":false,"PurchaseDate":"2017-05-15T08:46:07.521Z","ExpirationDate":"2019-04-16T04:18:51.761Z","Quantity":7},{"Name":"Watermelon","Type":"Produce","Store":"7-11","Expired":false,"PurchaseDate":"2015-06-11T11:45:21.634Z","ExpirationDate":"2019-06-23T01:14:53.35Z","Quantity":10},{"Name":"Tomatoes","Type":"Produce","Store":"Trader Joe's","Expired":false,"PurchaseDate":"2016-06-05T03:11:12.743Z","ExpirationDate":"2018-03-06T10:20:27.018Z","Quantity":2},{"Name":"Cheese","Type":"Dairy","Store":"Trader Joe's","Expired":false,"PurchaseDate":"2017-08-20T16:05:15.028Z","ExpirationDate":"2019-03-31T14:15:26.815Z","Quantity":5},{"Name":"Turnips","Type":"Produce","Store":"Trader Joe's","Expired":true,"PurchaseDate":"2018-06-29T19:37:13.3Z","ExpirationDate":"2017-11-05T14:52:26.852Z","Quantity":4},{"Name":"Broccoli","Type":"Produce","Store":"Grocery Outlet","Expired":false,"PurchaseDate":"2015-06-24T19:35:51.339Z","ExpirationDate":"2019-08-23T11:18:51.278Z","Quantity":3},{"Name":"Green onions","Type":"Produce","Store":"Trader Joe's","Expired":false,"PurchaseDate":"2018-03-29T21:57:02.09Z","ExpirationDate":"2018-04-11T17:22:20.111Z","Quantity":8},{"Name":"Peas","Type":"Produce","Store":"Albertsons","Expired":false,"PurchaseDate":"2018-04-08T09:29:54.65Z","ExpirationDate":"2019-08-22T01:32:42.625Z","Quantity":8},{"Name":"Rutabaga","Type":"Produce","Store":"Metropolitan Market","Expired":false,"PurchaseDate":"2016-02-28T07:59:30.248Z","ExpirationDate":"2018-03-22T15:36:51.768Z","Quantity":2},{"Name":"Spinach","Type":"Produce","Store":"QFC","Expired":false,"PurchaseDate":"2015-02-21T18:48:15.609Z","ExpirationDate":"2019-11-12T19:16:21.434Z","Quantity":3},{"Name":"Lamb","Type":"Meat","Store":"Grocery Outlet","Expired":false,"PurchaseDate":"2016-02-05T08:36:10.332Z","ExpirationDate":"2017-02-16T04:31:01.189Z","Quantity":1},{"Name":"Butter","Type":"Dairy","Store":"Trader Joe's","Expired":false,"PurchaseDate":"2018-07-21T09:53:56.181Z","ExpirationDate":"2018-10-31T03:25:13.561Z","Quantity":5},{"Name":"Arugula","Type":"Produce","Store":"QFC","Expired":false,"PurchaseDate":"2016-10-07T23:39:44.351Z","ExpirationDate":"2018-07-24T17:26:49.093Z","Quantity":2},{"Name":"Lamb","Type":"Meat","Store":"Trader Joe's","Expired":false,"PurchaseDate":"2017-04-26T22:09:54.392Z","ExpirationDate":"2017-09-20T22:38:12.151Z","Quantity":7},{"Name":"Milk","Type":"Dairy","Store":"Safeway","Expired":false,"PurchaseDate":"2015-08-25T00:50:04.73Z","ExpirationDate":"2019-10-14T22:16:42.259Z","Quantity":5},{"Name":"Eggplant","Type":"Produce","Store":"Grocery Outlet","Expired":false,"PurchaseDate":"2015-08-05T12:51:49.557Z","ExpirationDate":"2018-02-13T06:47:54.755Z","Quantity":10},{"Name":"Carrots","Type":"Produce","Store":"Albertsons","Expired":true,"PurchaseDate":"2017-12-16T19:58:31.163Z","ExpirationDate":"2017-06-19T21:08:18.894Z","Quantity":4},{"Name":"Turnips","Type":"Produce","Store":"Metropolitan Market","Expired":false,"PurchaseDate":"2017-02-08T08:52:34.041Z","ExpirationDate":"2018-06-12T21:06:51.975Z","Quantity":4},{"Name":"Rhubarb","Type":"Produce","Store":"QFC","Expired":false,"PurchaseDate":"2018-05-19T14:36:35.114Z","ExpirationDate":"2018-10-17T03:01:11.217Z","Quantity":3},{"Name":"Peppers","Type":"Produce","Store":"QFC","Expired":false,"PurchaseDate":"2015-05-17T10:57:43.938Z","ExpirationDate":"2018-10-31T18:11:41.526Z","Quantity":7},{"Name":"Peas","Type":"Produce","Store":"Safeway","Expired":false,"PurchaseDate":"2015-03-24T14:55:39.033Z","ExpirationDate":"2017-02-02T14:35:28.582Z","Quantity":2},{"Name":"Beets","Type":"Produce","Store":"Trader Joe's","Expired":false,"PurchaseDate":"2017-01-20T08:30:20.367Z","ExpirationDate":"2018-05-07T18:05:49.715Z","Quantity":4},{"Name":"Asparagus","Type":"Produce","Store":"Safeway","Expired":false,"PurchaseDate":"2015-09-19T12:39:22.86Z","ExpirationDate":"2017-05-18T13:32:33.758Z","Quantity":2},{"Name":"Eggplant","Type":"Produce","Store":"Grocery Outlet","Expired":false,"PurchaseDate":"2016-12-04T09:10:47.584Z","ExpirationDate":"2018-11-26T05:50:40.592Z","Quantity":1},{"Name":"Pork","Type":"Meat","Store":"7-11","Expired":false,"PurchaseDate":"2017-08-17T09:08:32.578Z","ExpirationDate":"2018-03-10T12:50:45.169Z","Quantity":7},{"Name":"Lettuce","Type":"Produce","Store":"Albertsons","Expired":false,"PurchaseDate":"2015-05-21T15:44:16.481Z","ExpirationDate":"2019-04-28T03:22:16.25Z","Quantity":4},{"Name":"Asparagus","Type":"Produce","Store":"Albertsons","Expired":false,"PurchaseDate":"2017-06-14T00:13:04.819Z","ExpirationDate":"2018-05-12T17:13:23.511Z","Quantity":10},{"Name":"Spinach","Type":"Produce","Store":"7-11","Expired":false,"PurchaseDate":"2016-09-04T23:54:04.67Z","ExpirationDate":"2018-10-11T00:41:11.398Z","Quantity":1},{"Name":"Tomatoes","Type":"Produce","Store":"Metropolitan Market","Expired":false,"PurchaseDate":"2015-10-30T11:22:03.755Z","ExpirationDate":"2019-09-26T23:59:00.661Z","Quantity":1},{"Name":"Peppers","Type":"Produce","Store":"Safeway","Expired":false,"PurchaseDate":"2016-12-09T12:24:10.276Z","ExpirationDate":"2019-03-04T13:12:51.631Z","Quantity":4},{"Name":"Peppers","Type":"Produce","Store":"Safeway","Expired":false,"PurchaseDate":"2017-03-29T14:13:00.061Z","ExpirationDate":"2019-08-13T00:57:21.82Z","Quantity":5},{"Name":"Asparagus","Type":"Produce","Store":"QFC","Expired":false,"PurchaseDate":"2016-08-12T00:46:20.107Z","ExpirationDate":"2017-05-31T10:15:24.875Z","Quantity":9},{"Name":"Cabbage","Type":"Produce","Store":"Trader Joe's","Expired":false,"PurchaseDate":"2015-11-27T11:10:22.943Z","ExpirationDate":"2017-10-24T21:23:25.953Z","Quantity":4},{"Name":"Yoghurt","Type":"Dairy","Store":"Safeway","Expired":false,"PurchaseDate":"2015-05-13T04:26:00.48Z","ExpirationDate":"2017-01-15T06:25:44.31Z","Quantity":10},{"Name":"Butter","Type":"Dairy","Store":"Trader Joe's","Expired":false,"PurchaseDate":"2016-03-10T03:15:42.085Z","ExpirationDate":"2017-05-16T19:24:51.082Z","Quantity":2},{"Name":"Cauliflower","Type":"Produce","Store":"Trader Joe's","Expired":false,"PurchaseDate":"2018-05-20T06:26:34.285Z","ExpirationDate":"2018-08-12T03:49:33.688Z","Quantity":10},{"Name":"Watermelon","Type":"Produce","Store":"Trader Joe's","Expired":false,"PurchaseDate":"2016-07-16T06:44:16.503Z","ExpirationDate":"2019-09-21T08:14:23.824Z","Quantity":2},{"Name":"Basil","Type":"Produce","Store":"Metropolitan Market","Expired":false,"PurchaseDate":"2016-08-04T06:14:25.651Z","ExpirationDate":"2017-12-08T15:33:35.553Z","Quantity":5},{"Name":"Lettuce","Type":"Produce","Store":"Metropolitan Market","Expired":false,"PurchaseDate":"2016-04-21T13:30:16.502Z","ExpirationDate":"2017-01-30T04:06:13.809Z","Quantity":9},{"Name":"Radish","Type":"Produce","Store":"Metropolitan Market","Expired":false,"PurchaseDate":"2017-02-17T08:33:57.874Z","ExpirationDate":"2018-05-10T04:50:44.094Z","Quantity":3},{"Name":"Okra","Type":"Produce","Store":"Safeway","Expired":false,"PurchaseDate":"2015-05-25T04:19:38.411Z","ExpirationDate":"2019-07-03T10:12:00.806Z","Quantity":9},{"Name":"Eggplant","Type":"Produce","Store":"Grocery Outlet","Expired":false,"PurchaseDate":"2015-08-04T04:40:45.531Z","ExpirationDate":"2017-07-23T17:08:06.593Z","Quantity":10},{"Name":"Onions","Type":"Produce","Store":"7-11","Expired":false,"PurchaseDate":"2018-04-24T06:23:42.334Z","ExpirationDate":"2018-11-06T10:16:27.817Z","Quantity":2},{"Name":"Fish","Type":"Meat","Store":"Safeway","Expired":false,"PurchaseDate":"2016-09-19T08:06:45.871Z","ExpirationDate":"2018-09-16T17:57:43.645Z","Quantity":5},{"Name":"Eggplant","Type":"Produce","Store":"Metropolitan Market","Expired":false,"PurchaseDate":"2017-09-24T14:26:47.075Z","ExpirationDate":"2018-07-26T18:00:22.751Z","Quantity":7},{"Name":"Fennel","Type":"Produce","Store":"Metropolitan Market","Expired":false,"PurchaseDate":"2016-03-28T14:36:11.327Z","ExpirationDate":"2019-11-06T06:02:35.773Z","Quantity":6},{"Name":"Tomatoes","Type":"Produce","Store":"QFC","Expired":false,"PurchaseDate":"2017-09-11T14:06:47.205Z","ExpirationDate":"2018-04-05T16:14:10.14Z","Quantity":9},{"Name":"Beets","Type":"Produce","Store":"Trader Joe's","Expired":false,"PurchaseDate":"2015-07-15T08:11:35.641Z","ExpirationDate":"2018-11-15T22:36:42.408Z","Quantity":3},{"Name":"Radish","Type":"Produce","Store":"Trader Joe's","Expired":false,"PurchaseDate":"2017-12-06T17:00:12.174Z","ExpirationDate":"2018-12-12T23:54:38.926Z","Quantity":4},{"Name":"Spinach","Type":"Produce","Store":"Metropolitan Market","Expired":true,"PurchaseDate":"2018-07-15T20:12:29.107Z","ExpirationDate":"2017-08-12T09:50:34.586Z","Quantity":3},{"Name":"Basil","Type":"Produce","Store":"Safeway","Expired":false,"PurchaseDate":"2015-06-30T10:58:17.704Z","ExpirationDate":"2019-04-28T17:57:37.213Z","Quantity":7},{"Name":"Turnips","Type":"Produce","Store":"Safeway","Expired":false,"PurchaseDate":"2015-01-03T05:58:30.013Z","ExpirationDate":"2019-01-02T18:24:30.613Z","Quantity":9},{"Name":"Rutabaga","Type":"Produce","Store":"Grocery Outlet","Expired":false,"PurchaseDate":"2016-01-18T04:59:27.645Z","ExpirationDate":"2018-10-26T13:40:30.111Z","Quantity":6},{"Name":"Arugula","Type":"Produce","Store":"Trader Joe's","Expired":false,"PurchaseDate":"2016-02-28T16:49:18.407Z","ExpirationDate":"2018-12-26T19:17:50.82Z","Quantity":5},{"Name":"Broccoli","Type":"Produce","Store":"Albertsons","Expired":false,"PurchaseDate":"2016-06-03T00:46:35.267Z","ExpirationDate":"2017-10-31T18:53:52.328Z","Quantity":1},{"Name":"Yoghurt","Type":"Dairy","Store":"Grocery Outlet","Expired":false,"PurchaseDate":"2016-08-02T23:04:46.526Z","ExpirationDate":"2017-01-12T02:27:53.022Z","Quantity":1},{"Name":"Arugula","Type":"Produce","Store":"Albertsons","Expired":false,"PurchaseDate":"2016-10-06T06:09:37.547Z","ExpirationDate":"2019-03-02T03:11:31.438Z","Quantity":3},{"Name":"Peas","Type":"Produce","Store":"Albertsons","Expired":false,"PurchaseDate":"2018-04-22T00:40:36.34Z","ExpirationDate":"2018-06-26T18:16:46.519Z","Quantity":8},{"Name":"Fish","Type":"Meat","Store":"QFC","Expired":false,"PurchaseDate":"2017-01-23T01:15:42.527Z","ExpirationDate":"2019-06-19T02:51:34.46Z","Quantity":9},{"Name":"Arugula","Type":"Produce","Store":"QFC","Expired":false,"PurchaseDate":"2016-06-30T04:01:07.214Z","ExpirationDate":"2017-12-03T15:25:56.818Z","Quantity":7},{"Name":"Arugula","Type":"Produce","Store":"Metropolitan Market","Expired":false,"PurchaseDate":"2018-04-07T05:58:46.235Z","ExpirationDate":"2018-07-04T07:33:52.42Z","Quantity":4},{"Name":"Green onions","Type":"Produce","Store":"Trader Joe's","Expired":false,"PurchaseDate":"2015-01-23T04:00:45.848Z","ExpirationDate":"2017-10-08T04:18:06.116Z","Quantity":3},{"Name":"Cheese","Type":"Dairy","Store":"Grocery Outlet","Expired":false,"PurchaseDate":"2016-12-24T15:10:12.13Z","ExpirationDate":"2018-02-07T01:09:14.294Z","Quantity":10},{"Name":"Tomatoes","Type":"Produce","Store":"Trader Joe's","Expired":false,"PurchaseDate":"2015-08-26T05:39:29.258Z","ExpirationDate":"2019-11-15T05:31:57.211Z","Quantity":5},{"Name":"Lettuce","Type":"Produce","Store":"Albertsons","Expired":false,"PurchaseDate":"2015-06-04T15:22:09.671Z","ExpirationDate":"2017-04-23T22:39:25.448Z","Quantity":10},{"Name":"Garlic","Type":"Produce","Store":"Trader Joe's","Expired":true,"PurchaseDate":"2017-07-03T03:45:26.293Z","ExpirationDate":"2017-05-20T11:41:01.742Z","Quantity":5},{"Name":"Rhubarb","Type":"Produce","Store":"Safeway","Expired":false,"PurchaseDate":"2017-07-24T17:53:29.599Z","ExpirationDate":"2018-02-25T23:04:38.768Z","Quantity":10},{"Name":"Tomatoes","Type":"Produce","Store":"QFC","Expired":false,"PurchaseDate":"2017-11-13T05:13:02.104Z","ExpirationDate":"2019-07-23T23:28:06.888Z","Quantity":4},{"Name":"Chard","Type":"Produce","Store":"Metropolitan Market","Expired":true,"PurchaseDate":"2018-05-11T00:54:42.854Z","ExpirationDate":"2017-12-07T13:25:27.631Z","Quantity":5},{"Name":"Milk","Type":"Dairy","Store":"Trader Joe's","Expired":false,"PurchaseDate":"2015-11-29T23:10:07.481Z","ExpirationDate":"2017-10-28T16:27:02.885Z","Quantity":7},{"Name":"Butter","Type":"Dairy","Store":"7-11","Expired":false,"PurchaseDate":"2016-03-17T05:51:34.722Z","ExpirationDate":"2018-03-04T16:17:00.439Z","Quantity":8},{"Name":"Green onions","Type":"Produce","Store":"Metropolitan Market","Expired":false,"PurchaseDate":"2016-09-21T09:00:43.728Z","ExpirationDate":"2017-12-14T20:04:05.095Z","Quantity":6},{"Name":"Carrots","Type":"Produce","Store":"Trader Joe's","Expired":false,"PurchaseDate":"2018-03-19T08:23:10.725Z","ExpirationDate":"2018-04-23T07:00:45.612Z","Quantity":3},{"Name":"Eggplant","Type":"Produce","Store":"Safeway","Expired":false,"PurchaseDate":"2017-04-28T09:33:38.264Z","ExpirationDate":"2019-11-28T05:26:42.734Z","Quantity":4},{"Name":"Tomatoes","Type":"Produce","Store":"Safeway","Expired":false,"PurchaseDate":"2017-04-25T16:04:27.507Z","ExpirationDate":"2019-03-16T11:24:55.345Z","Quantity":3},{"Name":"Fennel","Type":"Produce","Store":"Trader Joe's","Expired":false,"PurchaseDate":"2015-09-24T11:45:04.756Z","ExpirationDate":"2017-09-15T10:39:15.909Z","Quantity":7},{"Name":"Asparagus","Type":"Produce","Store":"Grocery Outlet","Expired":false,"PurchaseDate":"2016-12-14T10:55:09.46Z","ExpirationDate":"2019-11-24T04:30:38.889Z","Quantity":1},{"Name":"Broccoli","Type":"Produce","Store":"Metropolitan Market","Expired":false,"PurchaseDate":"2016-07-02T12:46:45.69Z","ExpirationDate":"2017-10-31T03:53:38.942Z","Quantity":2},{"Name":"Beef","Type":"Meat","Store":"Metropolitan Market","Expired":false,"PurchaseDate":"2018-02-22T09:14:59.139Z","ExpirationDate":"2018-11-06T18:18:37.25Z","Quantity":1},{"Name":"Tomatoes","Type":"Produce","Store":"Metropolitan Market","Expired":false,"PurchaseDate":"2018-04-26T03:56:31.73Z","ExpirationDate":"2018-10-27T10:46:06.083Z","Quantity":2},{"Name":"Watercress","Type":"Produce","Store":"Safeway","Expired":false,"PurchaseDate":"2016-11-25T09:12:08.987Z","ExpirationDate":"2018-10-26T17:01:00.554Z","Quantity":1},{"Name":"Garlic","Type":"Produce","Store":"Grocery Outlet","Expired":false,"PurchaseDate":"2017-06-02T05:28:36.119Z","ExpirationDate":"2019-11-25T16:31:13.327Z","Quantity":5},{"Name":"Peppers","Type":"Produce","Store":"Metropolitan Market","Expired":false,"PurchaseDate":"2017-05-04T14:58:23.289Z","ExpirationDate":"2019-02-01T01:33:00.211Z","Quantity":10},{"Name":"Green onions","Type":"Produce","Store":"Albertsons","Expired":false,"PurchaseDate":"2015-10-21T23:45:48.918Z","ExpirationDate":"2018-07-29T22:09:47.531Z","Quantity":8},{"Name":"Eggplant","Type":"Produce","Store":"QFC","Expired":true,"PurchaseDate":"2018-01-06T12:53:03.485Z","ExpirationDate":"2017-12-25T11:28:30.217Z","Quantity":3},{"Name":"Cabbage","Type":"Produce","Store":"Safeway","Expired":false,"PurchaseDate":"2016-05-07T14:30:16.315Z","ExpirationDate":"2017-06-17T11:28:38.322Z","Quantity":1},{"Name":"Eggplant","Type":"Produce","Store":"Safeway","Expired":false,"PurchaseDate":"2017-01-13T19:25:07.279Z","ExpirationDate":"2019-10-28T08:43:53.901Z","Quantity":2},{"Name":"Fennel","Type":"Produce","Store":"Grocery Outlet","Expired":false,"PurchaseDate":"2016-07-23T20:35:39.132Z","ExpirationDate":"2019-07-02T15:27:44.043Z","Quantity":3},{"Name":"Fennel","Type":"Produce","Store":"Grocery Outlet","Expired":false,"PurchaseDate":"2016-06-11T10:10:15.388Z","ExpirationDate":"2017-03-16T19:37:53.053Z","Quantity":8},{"Name":"Tomatoes","Type":"Produce","Store":"7-11","Expired":false,"PurchaseDate":"2017-01-25T09:06:54.117Z","ExpirationDate":"2017-07-11T23:37:42.049Z","Quantity":6},{"Name":"Eggplant","Type":"Produce","Store":"QFC","Expired":false,"PurchaseDate":"2017-06-08T12:13:06.382Z","ExpirationDate":"2017-08-03T05:28:55.081Z","Quantity":3},{"Name":"Cheese","Type":"Dairy","Store":"Grocery Outlet","Expired":false,"PurchaseDate":"2016-10-30T22:44:57.95Z","ExpirationDate":"2018-04-12T21:37:23.381Z","Quantity":9},{"Name":"Cabbage","Type":"Produce","Store":"Grocery Outlet","Expired":false,"PurchaseDate":"2017-04-24T04:50:08.786Z","ExpirationDate":"2018-03-26T07:47:48.23Z","Quantity":6},{"Name":"Chard","Type":"Produce","Store":"Safeway","Expired":false,"PurchaseDate":"2016-03-01T12:57:09.374Z","ExpirationDate":"2017-08-28T22:39:22.271Z","Quantity":6},{"Name":"Milk","Type":"Dairy","Store":"Trader Joe's","Expired":false,"PurchaseDate":"2017-03-30T09:23:37.32Z","ExpirationDate":"2019-06-02T20:27:13.268Z","Quantity":7},{"Name":"Lamb","Type":"Meat","Store":"Grocery Outlet","Expired":false,"PurchaseDate":"2015-03-14T08:29:15.079Z","ExpirationDate":"2017-04-08T05:10:51.027Z","Quantity":10},{"Name":"Garlic","Type":"Produce","Store":"Trader Joe's","Expired":false,"PurchaseDate":"2016-09-20T04:57:13.346Z","ExpirationDate":"2017-06-11T09:30:12.574Z","Quantity":10},{"Name":"Cucumbers","Type":"Produce","Store":"Grocery Outlet","Expired":false,"PurchaseDate":"2018-02-08T07:39:27.546Z","ExpirationDate":"2018-09-05T01:27:28.488Z","Quantity":5},{"Name":"Peas","Type":"Produce","Store":"Safeway","Expired":false,"PurchaseDate":"2017-11-10T03:52:04.38Z","ExpirationDate":"2018-09-23T21:58:00.249Z","Quantity":10},{"Name":"Milk","Type":"Dairy","Store":"Safeway","Expired":false,"PurchaseDate":"2016-09-07T17:32:49.122Z","ExpirationDate":"2019-12-01T10:49:32.876Z","Quantity":4},{"Name":"Tomatoes","Type":"Produce","Store":"Trader Joe's","Expired":false,"PurchaseDate":"2017-12-25T15:50:32.259Z","ExpirationDate":"2018-10-27T04:50:16.251Z","Quantity":10},{"Name":"Peas","Type":"Produce","Store":"Grocery Outlet","Expired":false,"PurchaseDate":"2017-11-23T11:40:10.322Z","ExpirationDate":"2019-03-31T23:22:25.337Z","Quantity":8},{"Name":"Potatoes","Type":"Produce","Store":"Safeway","Expired":true,"PurchaseDate":"2018-07-13T15:45:09.468Z","ExpirationDate":"2017-02-20T22:39:08.053Z","Quantity":1},{"Name":"Peppers","Type":"Produce","Store":"Metropolitan Market","Expired":false,"PurchaseDate":"2016-10-24T00:19:15.593Z","ExpirationDate":"2019-03-31T02:02:22.656Z","Quantity":4},{"Name":"Green onions","Type":"Produce","Store":"7-11","Expired":false,"PurchaseDate":"2016-02-29T16:34:15.629Z","ExpirationDate":"2018-10-19T07:45:52.119Z","Quantity":8},{"Name":"Yoghurt","Type":"Dairy","Store":"Grocery Outlet","Expired":false,"PurchaseDate":"2017-09-13T21:38:30.5Z","ExpirationDate":"2018-06-24T02:02:32.175Z","Quantity":7},{"Name":"Carrots","Type":"Produce","Store":"Safeway","Expired":false,"PurchaseDate":"2018-01-30T16:34:47.234Z","ExpirationDate":"2018-03-24T19:21:34.596Z","Quantity":4},{"Name":"Yoghurt","Type":"Dairy","Store":"7-11","Expired":true,"PurchaseDate":"2018-03-03T01:39:52.476Z","ExpirationDate":"2017-11-25T15:19:41.311Z","Quantity":7},{"Name":"Garlic","Type":"Produce","Store":"7-11","Expired":false,"PurchaseDate":"2015-03-28T00:23:14.361Z","ExpirationDate":"2019-03-13T19:09:16.155Z","Quantity":1},{"Name":"Potatoes","Type":"Produce","Store":"7-11","Expired":false,"PurchaseDate":"2018-06-19T08:33:56.584Z","ExpirationDate":"2019-03-16T03:07:32.848Z","Quantity":7},{"Name":"Cabbage","Type":"Produce","Store":"Grocery Outlet","Expired":true,"PurchaseDate":"2018-07-08T02:12:05.024Z","ExpirationDate":"2017-06-09T00:16:28.988Z","Quantity":6},{"Name":"Cauliflower","Type":"Produce","Store":"Trader Joe's","Expired":false,"PurchaseDate":"2018-01-27T07:14:49.456Z","ExpirationDate":"2019-09-22T22:37:17.474Z","Quantity":10},{"Name":"Okra","Type":"Produce","Store":"Metropolitan Market","Expired":false,"PurchaseDate":"2015-11-07T23:40:46.756Z","ExpirationDate":"2018-12-27T21:30:26.692Z","Quantity":4},{"Name":"Pork","Type":"Meat","Store":"Safeway","Expired":false,"PurchaseDate":"2015-12-28T13:34:29.151Z","ExpirationDate":"2019-11-25T03:03:39.285Z","Quantity":8},{"Name":"Potatoes","Type":"Produce","Store":"Grocery Outlet","Expired":false,"PurchaseDate":"2016-03-09T21:17:22.9Z","ExpirationDate":"2017-04-10T16:57:15.79Z","Quantity":3},{"Name":"Turnips","Type":"Produce","Store":"Albertsons","Expired":false,"PurchaseDate":"2017-07-02T15:37:06.136Z","ExpirationDate":"2018-01-05T12:36:56.845Z","Quantity":4},{"Name":"Garlic","Type":"Produce","Store":"Safeway","Expired":false,"PurchaseDate":"2017-07-29T12:58:08.753Z","ExpirationDate":"2017-08-09T19:42:06.414Z","Quantity":10},{"Name":"Ice cream","Type":"Dairy","Store":"Metropolitan Market","Expired":true,"PurchaseDate":"2018-03-31T06:48:42.741Z","ExpirationDate":"2018-01-19T18:40:28.482Z","Quantity":10},{"Name":"Watermelon","Type":"Produce","Store":"Grocery Outlet","Expired":false,"PurchaseDate":"2018-04-21T07:48:34.985Z","ExpirationDate":"2019-05-10T11:11:06.744Z","Quantity":6},{"Name":"Yoghurt","Type":"Dairy","Store":"Albertsons","Expired":true,"PurchaseDate":"2018-04-19T00:09:51.028Z","ExpirationDate":"2017-08-26T23:36:10.018Z","Quantity":2},{"Name":"Radish","Type":"Produce","Store":"Metropolitan Market","Expired":false,"PurchaseDate":"2016-10-18T11:04:02.815Z","ExpirationDate":"2019-12-10T04:28:05.703Z","Quantity":8},{"Name":"Chicken","Type":"Meat","Store":"Trader Joe's","Expired":false,"PurchaseDate":"2016-05-02T09:42:18.055Z","ExpirationDate":"2018-05-20T13:08:29.703Z","Quantity":2},{"Name":"Cheese","Type":"Dairy","Store":"Grocery Outlet","Expired":true,"PurchaseDate":"2017-11-02T11:16:55.657Z","ExpirationDate":"2017-04-14T16:34:15.043Z","Quantity":5},{"Name":"Peas","Type":"Produce","Store":"Albertsons","Expired":false,"PurchaseDate":"2018-02-15T19:53:59.666Z","ExpirationDate":"2019-09-28T23:21:51.531Z","Quantity":1},{"Name":"Zucchini","Type":"Produce","Store":"Safeway","Expired":false,"PurchaseDate":"2017-04-07T01:33:49.255Z","ExpirationDate":"2019-12-28T04:54:28.585Z","Quantity":7},{"Name":"Zucchini","Type":"Produce","Store":"7-11","Expired":false,"PurchaseDate":"2015-09-30T12:13:19.118Z","ExpirationDate":"2017-05-24T03:16:49.76Z","Quantity":9},{"Name":"Cucumbers","Type":"Produce","Store":"7-11","Expired":false,"PurchaseDate":"2016-09-21T07:11:33.382Z","ExpirationDate":"2017-11-17T16:35:28.397Z","Quantity":3},{"Name":"Arugula","Type":"Produce","Store":"QFC","Expired":true,"PurchaseDate":"2017-08-29T16:52:33.816Z","ExpirationDate":"2017-05-18T15:06:00.219Z","Quantity":9},{"Name":"Peppers","Type":"Produce","Store":"7-11","Expired":false,"PurchaseDate":"2015-09-18T04:33:03.093Z","ExpirationDate":"2017-06-25T15:30:15.845Z","Quantity":3},{"Name":"Tomatoes","Type":"Produce","Store":"QFC","Expired":false,"PurchaseDate":"2016-08-23T07:48:42.951Z","ExpirationDate":"2018-09-30T05:50:23.339Z","Quantity":5},{"Name":"Watercress","Type":"Produce","Store":"7-11","Expired":false,"PurchaseDate":"2018-03-02T05:44:18.238Z","ExpirationDate":"2019-05-02T17:59:05.662Z","Quantity":10},{"Name":"Asparagus","Type":"Produce","Store":"QFC","Expired":false,"PurchaseDate":"2015-09-03T00:42:29.732Z","ExpirationDate":"2018-10-23T17:19:47.004Z","Quantity":2},{"Name":"Arugula","Type":"Produce","Store":"QFC","Expired":false,"PurchaseDate":"2015-08-20T18:21:10.736Z","ExpirationDate":"2017-10-18T17:16:22.572Z","Quantity":6},{"Name":"Watermelon","Type":"Produce","Store":"Albertsons","Expired":false,"PurchaseDate":"2017-03-24T07:00:14.445Z","ExpirationDate":"2017-08-20T14:14:06.12Z","Quantity":10},{"Name":"Beets","Type":"Produce","Store":"Metropolitan Market","Expired":false,"PurchaseDate":"2018-05-24T11:01:11.661Z","ExpirationDate":"2018-10-24T02:10:10.857Z","Quantity":8},{"Name":"Green onions","Type":"Produce","Store":"Trader Joe's","Expired":false,"PurchaseDate":"2017-12-24T23:43:36.903Z","ExpirationDate":"2018-05-25T20:22:41.438Z","Quantity":1},{"Name":"Cauliflower","Type":"Produce","Store":"QFC","Expired":false,"PurchaseDate":"2017-09-25T20:43:51.946Z","ExpirationDate":"2019-08-20T02:11:20.93Z","Quantity":5},{"Name":"Radish","Type":"Produce","Store":"7-11","Expired":false,"PurchaseDate":"2016-06-26T14:19:05.066Z","ExpirationDate":"2017-04-17T22:37:10.762Z","Quantity":1},{"Name":"Tomatoes","Type":"Produce","Store":"QFC","Expired":false,"PurchaseDate":"2016-12-11T22:53:36.895Z","ExpirationDate":"2019-06-10T03:17:34.885Z","Quantity":2},{"Name":"Fish","Type":"Meat","Store":"7-11","Expired":true,"PurchaseDate":"2017-08-24T11:42:34.51Z","ExpirationDate":"2017-06-27T13:31:11.524Z","Quantity":10},{"Name":"Basil","Type":"Produce","Store":"QFC","Expired":false,"PurchaseDate":"2016-05-16T20:04:57.932Z","ExpirationDate":"2019-06-26T06:38:33.356Z","Quantity":7},{"Name":"Ice cream","Type":"Dairy","Store":"Safeway","Expired":false,"PurchaseDate":"2015-10-05T15:35:19.346Z","ExpirationDate":"2019-11-30T10:32:56.079Z","Quantity":9},{"Name":"Fish","Type":"Meat","Store":"Metropolitan Market","Expired":false,"PurchaseDate":"2016-03-04T17:55:36.641Z","ExpirationDate":"2017-06-27T07:09:52.306Z","Quantity":4},{"Name":"Fish","Type":"Meat","Store":"Trader Joe's","Expired":false,"PurchaseDate":"2016-06-13T17:19:38.935Z","ExpirationDate":"2019-07-11T20:10:36.091Z","Quantity":2},{"Name":"Watermelon","Type":"Produce","Store":"QFC","Expired":false,"PurchaseDate":"2016-05-21T06:10:16.086Z","ExpirationDate":"2017-11-05T18:25:35.715Z","Quantity":1},{"Name":"Basil","Type":"Produce","Store":"Albertsons","Expired":false,"PurchaseDate":"2017-01-11T03:25:04.131Z","ExpirationDate":"2017-04-24T17:59:26.495Z","Quantity":5},{"Name":"Milk","Type":"Dairy","Store":"Metropolitan Market","Expired":false,"PurchaseDate":"2016-06-02T13:25:09.661Z","ExpirationDate":"2019-04-27T01:10:49.966Z","Quantity":10},{"Name":"Onions","Type":"Produce","Store":"Albertsons","Expired":false,"PurchaseDate":"2016-01-05T08:43:16.913Z","ExpirationDate":"2017-06-17T01:49:24.085Z","Quantity":8},{"Name":"Rutabaga","Type":"Produce","Store":"7-11","Expired":false,"PurchaseDate":"2016-09-29T07:15:34.165Z","ExpirationDate":"2018-12-12T02:55:47.081Z","Quantity":9},{"Name":"Cabbage","Type":"Produce","Store":"Trader Joe's","Expired":true,"PurchaseDate":"2018-01-10T02:20:32.293Z","ExpirationDate":"2017-12-14T09:15:10.041Z","Quantity":6},{"Name":"Zucchini","Type":"Produce","Store":"Grocery Outlet","Expired":false,"PurchaseDate":"2016-02-07T12:41:53.155Z","ExpirationDate":"2018-10-01T20:49:35.988Z","Quantity":2},{"Name":"Cabbage","Type":"Produce","Store":"Albertsons","Expired":true,"PurchaseDate":"2018-08-13T21:11:05.048Z","ExpirationDate":"2017-12-08T13:44:20.764Z","Quantity":3},{"Name":"Peas","Type":"Produce","Store":"Metropolitan Market","Expired":false,"PurchaseDate":"2016-02-21T16:33:40.505Z","ExpirationDate":"2019-06-22T23:15:50.588Z","Quantity":7},{"Name":"Potatoes","Type":"Produce","Store":"7-11","Expired":false,"PurchaseDate":"2015-01-04T23:58:29.921Z","ExpirationDate":"2017-07-09T23:02:19.005Z","Quantity":8},{"Name":"Peppers","Type":"Produce","Store":"7-11","Expired":false,"PurchaseDate":"2015-03-23T13:05:47.561Z","ExpirationDate":"2017-04-14T11:48:33.848Z","Quantity":4},{"Name":"Beef","Type":"Meat","Store":"Metropolitan Market","Expired":false,"PurchaseDate":"2016-12-28T15:52:32.751Z","ExpirationDate":"2018-12-19T08:25:22.374Z","Quantity":10},{"Name":"Ice cream","Type":"Dairy","Store":"QFC","Expired":false,"PurchaseDate":"2017-01-13T09:20:34.746Z","ExpirationDate":"2018-01-25T15:02:39.605Z","Quantity":9},{"Name":"Zucchini","Type":"Produce","Store":"Grocery Outlet","Expired":true,"PurchaseDate":"2018-03-08T07:42:57.834Z","ExpirationDate":"2017-02-18T04:43:05.775Z","Quantity":5},{"Name":"Watermelon","Type":"Produce","Store":"Grocery Outlet","Expired":false,"PurchaseDate":"2017-07-31T20:48:07.64Z","ExpirationDate":"2019-04-09T01:05:58.471Z","Quantity":5},{"Name":"Arugula","Type":"Produce","Store":"Safeway","Expired":false,"PurchaseDate":"2015-01-27T03:43:01.726Z","ExpirationDate":"2019-10-15T09:21:26.916Z","Quantity":2},{"Name":"Butter","Type":"Dairy","Store":"QFC","Expired":false,"PurchaseDate":"2016-08-30T07:17:02.8Z","ExpirationDate":"2019-12-14T04:31:10.461Z","Quantity":10},{"Name":"Fennel","Type":"Produce","Store":"Safeway","Expired":false,"PurchaseDate":"2016-06-14T23:20:32.387Z","ExpirationDate":"2017-03-16T05:59:58.624Z","Quantity":1},{"Name":"Cucumbers","Type":"Produce","Store":"7-11","Expired":false,"PurchaseDate":"2015-11-03T06:42:30.627Z","ExpirationDate":"2019-03-15T05:01:19.956Z","Quantity":9},{"Name":"Chard","Type":"Produce","Store":"Safeway","Expired":false,"PurchaseDate":"2016-10-16T23:40:21.738Z","ExpirationDate":"2019-06-25T07:16:40.818Z","Quantity":9},{"Name":"Cabbage","Type":"Produce","Store":"Albertsons","Expired":false,"PurchaseDate":"2015-12-03T13:47:58.129Z","ExpirationDate":"2019-09-18T18:04:36.932Z","Quantity":4},{"Name":"Pork","Type":"Meat","Store":"QFC","Expired":false,"PurchaseDate":"2017-06-07T22:19:44.915Z","ExpirationDate":"2017-11-10T06:25:58.273Z","Quantity":2},{"Name":"Watercress","Type":"Produce","Store":"7-11","Expired":false,"PurchaseDate":"2016-01-21T08:35:09.545Z","ExpirationDate":"2018-02-10T09:56:56.514Z","Quantity":5},{"Name":"Cabbage","Type":"Produce","Store":"7-11","Expired":false,"PurchaseDate":"2017-07-08T17:39:14.143Z","ExpirationDate":"2019-11-19T22:36:24.965Z","Quantity":2},{"Name":"Potatoes","Type":"Produce","Store":"Metropolitan Market","Expired":true,"PurchaseDate":"2018-02-20T20:04:27.591Z","ExpirationDate":"2017-09-15T20:15:03.957Z","Quantity":2},{"Name":"Ice cream","Type":"Dairy","Store":"7-11","Expired":true,"PurchaseDate":"2018-05-20T23:11:23.071Z","ExpirationDate":"2017-01-10T04:43:08.96Z","Quantity":2},{"Name":"Ice cream","Type":"Dairy","Store":"7-11","Expired":false,"PurchaseDate":"2018-01-22T13:50:53.472Z","ExpirationDate":"2019-07-04T07:26:18.154Z","Quantity":8},{"Name":"Basil","Type":"Produce","Store":"QFC","Expired":false,"PurchaseDate":"2018-06-14T20:01:17.263Z","ExpirationDate":"2019-01-30T00:10:33.777Z","Quantity":8},{"Name":"Zucchini","Type":"Produce","Store":"Trader Joe's","Expired":false,"PurchaseDate":"2017-02-21T02:19:42.617Z","ExpirationDate":"2017-11-11T00:44:51.719Z","Quantity":6},{"Name":"Chard","Type":"Produce","Store":"Metropolitan Market","Expired":false,"PurchaseDate":"2016-04-27T08:26:40.633Z","ExpirationDate":"2019-01-17T14:41:30.103Z","Quantity":7},{"Name":"Zucchini","Type":"Produce","Store":"Albertsons","Expired":false,"PurchaseDate":"2016-07-10T13:42:26.753Z","ExpirationDate":"2018-10-07T12:47:11.95Z","Quantity":10},{"Name":"Carrots","Type":"Produce","Store":"Metropolitan Market","Expired":false,"PurchaseDate":"2018-06-24T09:35:48.333Z","ExpirationDate":"2019-01-16T14:15:12.69Z","Quantity":7},{"Name":"Cucumbers","Type":"Produce","Store":"Trader Joe's","Expired":false,"PurchaseDate":"2016-04-16T14:52:16.508Z","ExpirationDate":"2019-05-12T05:03:20.115Z","Quantity":6},{"Name":"Beef","Type":"Meat","Store":"7-11","Expired":false,"PurchaseDate":"2015-12-26T23:02:25.279Z","ExpirationDate":"2019-10-12T04:11:46.731Z","Quantity":1},{"Name":"Carrots","Type":"Produce","Store":"7-11","Expired":false,"PurchaseDate":"2016-07-27T20:35:30.516Z","ExpirationDate":"2019-12-01T17:46:38.266Z","Quantity":7},{"Name":"Zucchini","Type":"Produce","Store":"Trader Joe's","Expired":false,"PurchaseDate":"2016-06-22T02:54:22.49Z","ExpirationDate":"2019-09-29T21:24:50.064Z","Quantity":9},{"Name":"Lettuce","Type":"Produce","Store":"QFC","Expired":false,"PurchaseDate":"2016-07-18T18:19:48.118Z","ExpirationDate":"2019-03-08T02:51:42.509Z","Quantity":6},{"Name":"Milk","Type":"Dairy","Store":"Trader Joe's","Expired":false,"PurchaseDate":"2016-08-27T10:31:12.548Z","ExpirationDate":"2017-08-15T21:58:27.734Z","Quantity":10},{"Name":"Chard","Type":"Produce","Store":"Albertsons","Expired":false,"PurchaseDate":"2017-09-17T19:56:58.365Z","ExpirationDate":"2017-09-29T13:24:05.21Z","Quantity":2},{"Name":"Yoghurt","Type":"Dairy","Store":"QFC","Expired":false,"PurchaseDate":"2015-09-13T15:41:55.207Z","ExpirationDate":"2017-11-26T17:26:04.831Z","Quantity":1},{"Name":"Beets","Type":"Produce","Store":"7-11","Expired":false,"PurchaseDate":"2016-04-16T15:46:47.301Z","ExpirationDate":"2018-11-03T09:17:32.682Z","Quantity":7},{"Name":"Green onions","Type":"Produce","Store":"Albertsons","Expired":false,"PurchaseDate":"2015-11-07T08:42:14.737Z","ExpirationDate":"2019-10-19T02:04:08.655Z","Quantity":7},{"Name":"Rhubarb","Type":"Produce","Store":"QFC","Expired":false,"PurchaseDate":"2015-09-23T07:52:58.42Z","ExpirationDate":"2017-05-13T01:27:01.36Z","Quantity":10},{"Name":"Cabbage","Type":"Produce","Store":"QFC","Expired":false,"PurchaseDate":"2015-07-25T20:29:43.307Z","ExpirationDate":"2017-01-27T11:53:13.457Z","Quantity":5},{"Name":"Spinach","Type":"Produce","Store":"7-11","Expired":false,"PurchaseDate":"2016-08-31T22:09:18.111Z","ExpirationDate":"2018-10-03T01:20:41.541Z","Quantity":2},{"Name":"Fish","Type":"Meat","Store":"Grocery Outlet","Expired":false,"PurchaseDate":"2016-10-24T05:39:43.227Z","ExpirationDate":"2019-06-22T14:09:16.782Z","Quantity":1},{"Name":"Chard","Type":"Produce","Store":"QFC","Expired":true,"PurchaseDate":"2017-11-13T13:52:24.257Z","ExpirationDate":"2017-03-20T06:23:34.657Z","Quantity":2},{"Name":"Carrots","Type":"Produce","Store":"Trader Joe's","Expired":false,"PurchaseDate":"2017-02-01T20:13:01.354Z","ExpirationDate":"2018-02-15T19:58:16.214Z","Quantity":9},{"Name":"Carrots","Type":"Produce","Store":"Albertsons","Expired":false,"PurchaseDate":"2015-08-18T22:13:16.547Z","ExpirationDate":"2019-04-13T08:56:37.673Z","Quantity":5},{"Name":"Watermelon","Type":"Produce","Store":"7-11","Expired":false,"PurchaseDate":"2017-01-19T16:54:07.186Z","ExpirationDate":"2018-12-20T13:34:22.007Z","Quantity":10},{"Name":"Green onions","Type":"Produce","Store":"Metropolitan Market","Expired":false,"PurchaseDate":"2015-11-11T19:58:04.725Z","ExpirationDate":"2018-01-06T10:39:56.777Z","Quantity":4},{"Name":"Cabbage","Type":"Produce","Store":"Grocery Outlet","Expired":false,"PurchaseDate":"2016-10-23T14:10:19.469Z","ExpirationDate":"2017-06-10T21:40:09.968Z","Quantity":9},{"Name":"Watermelon","Type":"Produce","Store":"Grocery Outlet","Expired":false,"PurchaseDate":"2016-06-01T18:03:11.854Z","ExpirationDate":"2019-02-07T12:46:55.491Z","Quantity":5},{"Name":"Watercress","Type":"Produce","Store":"Metropolitan Market","Expired":false,"PurchaseDate":"2018-04-15T09:19:07.635Z","ExpirationDate":"2018-10-25T19:42:54.971Z","Quantity":9},{"Name":"Cheese","Type":"Dairy","Store":"Metropolitan Market","Expired":false,"PurchaseDate":"2015-02-03T01:23:27.284Z","ExpirationDate":"2018-03-10T12:35:55.611Z","Quantity":7},{"Name":"Basil","Type":"Produce","Store":"Safeway","Expired":false,"PurchaseDate":"2017-05-17T20:30:51.335Z","ExpirationDate":"2018-03-09T08:03:47.859Z","Quantity":4},{"Name":"Eggplant","Type":"Produce","Store":"Albertsons","Expired":false,"PurchaseDate":"2015-12-03T11:07:38.818Z","ExpirationDate":"2019-02-15T20:40:38.094Z","Quantity":10},{"Name":"Okra","Type":"Produce","Store":"Safeway","Expired":false,"PurchaseDate":"2015-05-18T19:22:12.095Z","ExpirationDate":"2017-03-27T07:50:15.931Z","Quantity":2},{"Name":"Beets","Type":"Produce","Store":"QFC","Expired":false,"PurchaseDate":"2016-08-26T03:55:36.233Z","ExpirationDate":"2019-05-02T12:31:09.421Z","Quantity":8},{"Name":"Fennel","Type":"Produce","Store":"Trader Joe's","Expired":false,"PurchaseDate":"2015-06-28T19:28:11.461Z","ExpirationDate":"2019-11-05T10:08:36.212Z","Quantity":1},{"Name":"Radish","Type":"Produce","Store":"Metropolitan Market","Expired":true,"PurchaseDate":"2018-01-04T01:09:00.595Z","ExpirationDate":"2017-12-03T03:34:03.067Z","Quantity":1},{"Name":"Beef","Type":"Meat","Store":"7-11","Expired":false,"PurchaseDate":"2017-03-21T21:42:10.46Z","ExpirationDate":"2019-10-23T09:43:12.807Z","Quantity":8},{"Name":"Cheese","Type":"Dairy","Store":"Trader Joe's","Expired":false,"PurchaseDate":"2015-03-23T02:37:08.771Z","ExpirationDate":"2018-01-06T09:16:02.444Z","Quantity":8},{"Name":"Beets","Type":"Produce","Store":"Grocery Outlet","Expired":false,"PurchaseDate":"2016-01-03T13:03:42.267Z","ExpirationDate":"2018-03-25T15:07:27.218Z","Quantity":8},{"Name":"Fish","Type":"Meat","Store":"QFC","Expired":true,"PurchaseDate":"2017-10-09T14:06:57.321Z","ExpirationDate":"2017-01-28T10:04:20.289Z","Quantity":7},{"Name":"Potatoes","Type":"Produce","Store":"Safeway","Expired":false,"PurchaseDate":"2015-05-28T16:45:33.348Z","ExpirationDate":"2018-03-30T13:36:46.799Z","Quantity":9},{"Name":"Turnips","Type":"Produce","Store":"Metropolitan Market","Expired":false,"PurchaseDate":"2015-03-09T02:50:11.853Z","ExpirationDate":"2019-11-28T00:52:31.02Z","Quantity":7},{"Name":"Cheese","Type":"Dairy","Store":"Metropolitan Market","Expired":false,"PurchaseDate":"2017-07-19T12:19:48.438Z","ExpirationDate":"2019-11-11T23:47:11.258Z","Quantity":8},{"Name":"Peppers","Type":"Produce","Store":"Grocery Outlet","Expired":false,"PurchaseDate":"2017-08-26T11:00:59.575Z","ExpirationDate":"2017-11-20T21:58:53.092Z","Quantity":10},{"Name":"Yoghurt","Type":"Dairy","Store":"Metropolitan Market","Expired":false,"PurchaseDate":"2017-02-17T07:35:58.066Z","ExpirationDate":"2019-08-29T09:03:44.124Z","Quantity":8},{"Name":"Onions","Type":"Produce","Store":"Trader Joe's","Expired":false,"PurchaseDate":"2016-02-03T07:46:00.401Z","ExpirationDate":"2018-11-25T19:15:46.592Z","Quantity":9},{"Name":"Watercress","Type":"Produce","Store":"QFC","Expired":false,"PurchaseDate":"2015-12-07T04:58:05.164Z","ExpirationDate":"2019-07-23T21:46:43.305Z","Quantity":6},{"Name":"Lettuce","Type":"Produce","Store":"Trader Joe's","Expired":false,"PurchaseDate":"2017-02-27T22:16:19.683Z","ExpirationDate":"2019-11-07T10:35:58.51Z","Quantity":1},{"Name":"Green onions","Type":"Produce","Store":"Safeway","Expired":false,"PurchaseDate":"2015-06-26T20:06:23.41Z","ExpirationDate":"2018-03-17T23:13:39.684Z","Quantity":6},{"Name":"Rutabaga","Type":"Produce","Store":"QFC","Expired":false,"PurchaseDate":"2016-05-29T17:48:53.406Z","ExpirationDate":"2017-08-13T19:34:27.629Z","Quantity":8},{"Name":"Yoghurt","Type":"Dairy","Store":"Safeway","Expired":false,"PurchaseDate":"2017-11-13T11:19:56.938Z","ExpirationDate":"2019-03-22T16:23:18.462Z","Quantity":5},{"Name":"Cucumbers","Type":"Produce","Store":"Metropolitan Market","Expired":true,"PurchaseDate":"2018-08-16T17:00:58.48Z","ExpirationDate":"2017-01-30T21:05:21.858Z","Quantity":6},{"Name":"Beets","Type":"Produce","Store":"7-11","Expired":false,"PurchaseDate":"2017-08-14T19:40:02.328Z","ExpirationDate":"2017-12-25T07:30:42.866Z","Quantity":8},{"Name":"Cucumbers","Type":"Produce","Store":"Safeway","Expired":false,"PurchaseDate":"2018-04-24T05:52:56.557Z","ExpirationDate":"2019-01-21T09:18:36.069Z","Quantity":10},{"Name":"Carrots","Type":"Produce","Store":"Metropolitan Market","Expired":false,"PurchaseDate":"2016-10-22T15:51:00.823Z","ExpirationDate":"2019-03-24T18:38:31.867Z","Quantity":5},{"Name":"Eggplant","Type":"Produce","Store":"Metropolitan Market","Expired":true,"PurchaseDate":"2017-08-30T04:59:27.713Z","ExpirationDate":"2017-05-16T10:11:31.438Z","Quantity":1},{"Name":"Radish","Type":"Produce","Store":"Metropolitan Market","Expired":false,"PurchaseDate":"2016-07-03T09:00:39.648Z","ExpirationDate":"2019-10-13T01:50:31.696Z","Quantity":3},{"Name":"Basil","Type":"Produce","Store":"Albertsons","Expired":true,"PurchaseDate":"2018-07-23T07:52:47.971Z","ExpirationDate":"2018-02-20T15:14:57.355Z","Quantity":2},{"Name":"Chicken","Type":"Meat","Store":"Grocery Outlet","Expired":false,"PurchaseDate":"2015-04-15T17:59:04.582Z","ExpirationDate":"2017-12-20T22:04:35.359Z","Quantity":6},{"Name":"Spinach","Type":"Produce","Store":"Safeway","Expired":false,"PurchaseDate":"2018-04-30T03:56:57.972Z","ExpirationDate":"2019-08-11T04:52:41.927Z","Quantity":7},{"Name":"Butter","Type":"Dairy","Store":"Safeway","Expired":true,"PurchaseDate":"2018-01-20T11:12:14.923Z","ExpirationDate":"2017-05-04T12:56:43.025Z","Quantity":2},{"Name":"Eggplant","Type":"Produce","Store":"Grocery Outlet","Expired":false,"PurchaseDate":"2016-03-28T19:41:05.406Z","ExpirationDate":"2017-01-09T09:34:31.807Z","Quantity":6},{"Name":"Peas","Type":"Produce","Store":"Trader Joe's","Expired":false,"PurchaseDate":"2018-07-29T12:02:52.166Z","ExpirationDate":"2018-10-13T12:27:27.791Z","Quantity":8},{"Name":"Lettuce","Type":"Produce","Store":"Safeway","Expired":false,"PurchaseDate":"2016-09-03T12:22:44.896Z","ExpirationDate":"2017-11-19T02:51:10.947Z","Quantity":1},{"Name":"Beets","Type":"Produce","Store":"Metropolitan Market","Expired":true,"PurchaseDate":"2018-04-24T13:28:36.75Z","ExpirationDate":"2017-12-06T02:03:13.553Z","Quantity":7},{"Name":"Eggplant","Type":"Produce","Store":"Albertsons","Expired":false,"PurchaseDate":"2017-11-19T06:13:02.528Z","ExpirationDate":"2018-12-01T08:25:05.341Z","Quantity":2},{"Name":"Zucchini","Type":"Produce","Store":"7-11","Expired":false,"PurchaseDate":"2015-12-28T12:49:29.137Z","ExpirationDate":"2017-01-19T18:44:34.779Z","Quantity":7},{"Name":"Cabbage","Type":"Produce","Store":"Trader Joe's","Expired":false,"PurchaseDate":"2018-03-31T08:38:33.02Z","ExpirationDate":"2018-05-12T17:52:23.275Z","Quantity":9},{"Name":"Turnips","Type":"Produce","Store":"QFC","Expired":false,"PurchaseDate":"2015-09-19T22:43:28.625Z","ExpirationDate":"2018-12-01T16:39:35.513Z","Quantity":3},{"Name":"Watercress","Type":"Produce","Store":"7-11","Expired":true,"PurchaseDate":"2018-04-26T00:33:42.163Z","ExpirationDate":"2017-05-13T01:56:48.821Z","Quantity":4},{"Name":"Garlic","Type":"Produce","Store":"Trader Joe's","Expired":false,"PurchaseDate":"2017-04-29T11:55:13.069Z","ExpirationDate":"2019-11-29T15:26:46.157Z","Quantity":3},{"Name":"Fish","Type":"Meat","Store":"Grocery Outlet","Expired":false,"PurchaseDate":"2017-07-28T13:09:25.193Z","ExpirationDate":"2019-06-29T13:08:30.981Z","Quantity":4},{"Name":"Radish","Type":"Produce","Store":"Trader Joe's","Expired":false,"PurchaseDate":"2016-12-09T07:06:49.493Z","ExpirationDate":"2019-03-08T02:35:33.033Z","Quantity":8},{"Name":"Asparagus","Type":"Produce","Store":"7-11","Expired":false,"PurchaseDate":"2017-02-05T10:05:01.551Z","ExpirationDate":"2017-08-29T12:27:46.434Z","Quantity":4},{"Name":"Fennel","Type":"Produce","Store":"7-11","Expired":true,"PurchaseDate":"2018-05-25T19:30:38.577Z","ExpirationDate":"2017-11-28T05:11:51.882Z","Quantity":9},{"Name":"Okra","Type":"Produce","Store":"Metropolitan Market","Expired":false,"PurchaseDate":"2015-07-05T03:13:34.608Z","ExpirationDate":"2017-04-03T04:50:16.241Z","Quantity":7},{"Name":"Okra","Type":"Produce","Store":"Grocery Outlet","Expired":false,"PurchaseDate":"2016-10-17T10:33:19.845Z","ExpirationDate":"2019-04-27T18:30:54.363Z","Quantity":10},{"Name":"Lettuce","Type":"Produce","Store":"Metropolitan Market","Expired":false,"PurchaseDate":"2017-02-09T22:23:10.739Z","ExpirationDate":"2017-11-23T10:32:49.636Z","Quantity":8},{"Name":"Cabbage","Type":"Produce","Store":"Safeway","Expired":false,"PurchaseDate":"2017-05-01T18:36:34.981Z","ExpirationDate":"2017-08-03T01:02:09.097Z","Quantity":6},{"Name":"Ice cream","Type":"Dairy","Store":"Safeway","Expired":false,"PurchaseDate":"2015-02-10T21:46:32.458Z","ExpirationDate":"2019-06-10T15:59:55.892Z","Quantity":1},{"Name":"Cabbage","Type":"Produce","Store":"Trader Joe's","Expired":false,"PurchaseDate":"2015-12-06T06:15:20.783Z","ExpirationDate":"2018-09-28T07:50:33.06Z","Quantity":9},{"Name":"Onions","Type":"Produce","Store":"Albertsons","Expired":false,"PurchaseDate":"2015-09-11T17:58:12.269Z","ExpirationDate":"2017-09-17T10:45:30.515Z","Quantity":9},{"Name":"Butter","Type":"Dairy","Store":"7-11","Expired":false,"PurchaseDate":"2015-05-11T16:14:17.702Z","ExpirationDate":"2019-12-07T19:01:09.459Z","Quantity":4},{"Name":"Radish","Type":"Produce","Store":"Grocery Outlet","Expired":false,"PurchaseDate":"2018-06-30T19:27:48.175Z","ExpirationDate":"2019-08-05T10:03:09.506Z","Quantity":9},{"Name":"Broccoli","Type":"Produce","Store":"Safeway","Expired":true,"PurchaseDate":"2018-01-13T21:08:07.133Z","ExpirationDate":"2017-10-17T12:40:47.721Z","Quantity":7},{"Name":"Chicken","Type":"Meat","Store":"QFC","Expired":false,"PurchaseDate":"2017-05-19T10:00:34.048Z","ExpirationDate":"2019-09-08T18:05:16.002Z","Quantity":1},{"Name":"Onions","Type":"Produce","Store":"7-11","Expired":false,"PurchaseDate":"2016-10-07T08:35:34.87Z","ExpirationDate":"2018-01-12T06:15:00.712Z","Quantity":10},{"Name":"Cauliflower","Type":"Produce","Store":"Trader Joe's","Expired":false,"PurchaseDate":"2016-07-03T13:26:23.799Z","ExpirationDate":"2018-09-15T09:02:25.841Z","Quantity":1},{"Name":"Peppers","Type":"Produce","Store":"Trader Joe's","Expired":false,"PurchaseDate":"2016-09-13T01:55:08.36Z","ExpirationDate":"2018-12-02T17:17:30.48Z","Quantity":2},{"Name":"Rutabaga","Type":"Produce","Store":"Trader Joe's","Expired":false,"PurchaseDate":"2016-01-02T10:39:52.064Z","ExpirationDate":"2017-03-30T03:11:23.817Z","Quantity":6},{"Name":"Butter","Type":"Dairy","Store":"Trader Joe's","Expired":false,"PurchaseDate":"2018-02-18T23:33:45.309Z","ExpirationDate":"2019-03-16T15:06:17.947Z","Quantity":2},{"Name":"Chicken","Type":"Meat","Store":"Grocery Outlet","Expired":false,"PurchaseDate":"2015-07-29T00:29:46.64Z","ExpirationDate":"2019-10-04T22:54:39.185Z","Quantity":9},{"Name":"Chard","Type":"Produce","Store":"Metropolitan Market","Expired":true,"PurchaseDate":"2018-03-31T02:34:57.944Z","ExpirationDate":"2017-07-05T01:19:08.627Z","Quantity":3},{"Name":"Turnips","Type":"Produce","Store":"Albertsons","Expired":false,"PurchaseDate":"2017-10-22T04:09:58.899Z","ExpirationDate":"2019-08-21T19:56:07.708Z","Quantity":9},{"Name":"Okra","Type":"Produce","Store":"Metropolitan Market","Expired":false,"PurchaseDate":"2015-04-27T07:46:48.655Z","ExpirationDate":"2017-03-17T18:01:43.616Z","Quantity":2},{"Name":"Watermelon","Type":"Produce","Store":"Metropolitan Market","Expired":false,"PurchaseDate":"2015-02-26T00:50:10.048Z","ExpirationDate":"2018-11-30T04:34:34.198Z","Quantity":6},{"Name":"Pork","Type":"Meat","Store":"Metropolitan Market","Expired":false,"PurchaseDate":"2015-06-25T21:50:03.68Z","ExpirationDate":"2017-01-19T05:34:06.799Z","Quantity":10},{"Name":"Radish","Type":"Produce","Store":"7-11","Expired":false,"PurchaseDate":"2016-05-07T15:10:24.964Z","ExpirationDate":"2019-09-25T10:03:18.621Z","Quantity":5},{"Name":"Cheese","Type":"Dairy","Store":"Safeway","Expired":false,"PurchaseDate":"2016-08-10T13:20:09.005Z","ExpirationDate":"2019-07-21T20:37:20.084Z","Quantity":3},{"Name":"Rutabaga","Type":"Produce","Store":"Albertsons","Expired":false,"PurchaseDate":"2018-07-19T11:48:49.426Z","ExpirationDate":"2019-05-18T12:10:13.754Z","Quantity":4},{"Name":"Pork","Type":"Meat","Store":"QFC","Expired":false,"PurchaseDate":"2016-08-24T07:45:31.382Z","ExpirationDate":"2018-04-27T11:16:46.73Z","Quantity":7},{"Name":"Chicken","Type":"Meat","Store":"Albertsons","Expired":false,"PurchaseDate":"2017-03-24T20:02:41.357Z","ExpirationDate":"2019-11-07T21:21:02.069Z","Quantity":5},{"Name":"Watermelon","Type":"Produce","Store":"Metropolitan Market","Expired":false,"PurchaseDate":"2017-10-03T09:51:25.954Z","ExpirationDate":"2017-12-28T02:32:11.658Z","Quantity":7},{"Name":"Ice cream","Type":"Dairy","Store":"7-11","Expired":false,"PurchaseDate":"2016-07-18T03:45:49.725Z","ExpirationDate":"2019-08-06T18:57:31.96Z","Quantity":2},{"Name":"Chicken","Type":"Meat","Store":"Metropolitan Market","Expired":false,"PurchaseDate":"2015-01-24T06:25:48.543Z","ExpirationDate":"2018-09-11T18:04:00.83Z","Quantity":4},{"Name":"Tomatoes","Type":"Produce","Store":"Albertsons","Expired":false,"PurchaseDate":"2016-01-21T01:29:56.824Z","ExpirationDate":"2017-01-20T17:17:02.746Z","Quantity":6},{"Name":"Watercress","Type":"Produce","Store":"Grocery Outlet","Expired":false,"PurchaseDate":"2018-04-26T04:39:41.796Z","ExpirationDate":"2019-08-27T00:59:28.414Z","Quantity":2},{"Name":"Arugula","Type":"Produce","Store":"Trader Joe's","Expired":true,"PurchaseDate":"2018-06-13T07:11:33.722Z","ExpirationDate":"2017-01-21T21:13:39.807Z","Quantity":9},{"Name":"Milk","Type":"Dairy","Store":"7-11","Expired":false,"PurchaseDate":"2015-01-10T01:39:08.538Z","ExpirationDate":"2017-01-16T06:09:33.655Z","Quantity":2},{"Name":"Pork","Type":"Meat","Store":"Metropolitan Market","Expired":false,"PurchaseDate":"2016-09-21T10:25:58.831Z","ExpirationDate":"2018-05-12T10:03:23.508Z","Quantity":6},{"Name":"Broccoli","Type":"Produce","Store":"Trader Joe's","Expired":false,"PurchaseDate":"2017-04-13T18:20:26.729Z","ExpirationDate":"2017-10-31T07:48:57.89Z","Quantity":2},{"Name":"Eggplant","Type":"Produce","Store":"Grocery Outlet","Expired":false,"PurchaseDate":"2018-03-01T21:37:49.262Z","ExpirationDate":"2019-05-01T07:45:04.691Z","Quantity":2},{"Name":"Butter","Type":"Dairy","Store":"Grocery Outlet","Expired":false,"PurchaseDate":"2015-12-02T02:42:14.471Z","ExpirationDate":"2017-10-18T16:31:09.387Z","Quantity":6},{"Name":"Spinach","Type":"Produce","Store":"Grocery Outlet","Expired":false,"PurchaseDate":"2017-04-19T23:26:53.091Z","ExpirationDate":"2019-08-24T10:43:55.643Z","Quantity":9},{"Name":"Rhubarb","Type":"Produce","Store":"Albertsons","Expired":false,"PurchaseDate":"2018-01-28T19:49:40.997Z","ExpirationDate":"2018-10-11T12:05:14.582Z","Quantity":5},{"Name":"Pork","Type":"Meat","Store":"Grocery Outlet","Expired":false,"PurchaseDate":"2015-04-28T22:38:40.66Z","ExpirationDate":"2017-01-19T06:54:50.998Z","Quantity":2},{"Name":"Tomatoes","Type":"Produce","Store":"Safeway","Expired":false,"PurchaseDate":"2017-07-14T23:09:37.862Z","ExpirationDate":"2019-04-11T11:56:31.474Z","Quantity":5},{"Name":"Radish","Type":"Produce","Store":"7-11","Expired":false,"PurchaseDate":"2015-05-04T14:42:04.563Z","ExpirationDate":"2019-02-27T12:10:58.405Z","Quantity":1},{"Name":"Lettuce","Type":"Produce","Store":"QFC","Expired":false,"PurchaseDate":"2018-05-13T18:25:42.746Z","ExpirationDate":"2018-11-24T16:34:03.652Z","Quantity":10},{"Name":"Okra","Type":"Produce","Store":"Albertsons","Expired":false,"PurchaseDate":"2016-05-25T13:53:10.254Z","ExpirationDate":"2017-07-05T10:58:49.939Z","Quantity":5},{"Name":"Okra","Type":"Produce","Store":"QFC","Expired":false,"PurchaseDate":"2015-03-13T00:26:33.561Z","ExpirationDate":"2019-01-06T20:23:45.099Z","Quantity":2},{"Name":"Milk","Type":"Dairy","Store":"QFC","Expired":false,"PurchaseDate":"2015-06-08T03:05:59.586Z","ExpirationDate":"2018-04-01T01:53:50.802Z","Quantity":9},{"Name":"Cabbage","Type":"Produce","Store":"Albertsons","Expired":false,"PurchaseDate":"2015-02-09T14:40:41.947Z","ExpirationDate":"2018-04-15T09:36:18.592Z","Quantity":5},{"Name":"Rutabaga","Type":"Produce","Store":"7-11","Expired":false,"PurchaseDate":"2015-07-02T11:18:01.541Z","ExpirationDate":"2017-05-15T00:14:09.999Z","Quantity":4},{"Name":"Lettuce","Type":"Produce","Store":"QFC","Expired":false,"PurchaseDate":"2017-03-19T07:54:11.45Z","ExpirationDate":"2017-12-02T02:00:47.144Z","Quantity":2},{"Name":"Green onions","Type":"Produce","Store":"Safeway","Expired":false,"PurchaseDate":"2017-03-14T16:10:10.313Z","ExpirationDate":"2017-07-24T04:09:46.377Z","Quantity":1},{"Name":"Onions","Type":"Produce","Store":"7-11","Expired":false,"PurchaseDate":"2015-10-12T06:55:08.704Z","ExpirationDate":"2018-06-11T06:49:43.565Z","Quantity":8},{"Name":"Garlic","Type":"Produce","Store":"Grocery Outlet","Expired":false,"PurchaseDate":"2018-05-26T06:29:16.251Z","ExpirationDate":"2019-02-22T01:12:20.315Z","Quantity":4},{"Name":"Spinach","Type":"Produce","Store":"Safeway","Expired":false,"PurchaseDate":"2015-02-01T03:48:16.239Z","ExpirationDate":"2017-02-15T02:09:55.686Z","Quantity":1},{"Name":"Cabbage","Type":"Produce","Store":"Metropolitan Market","Expired":false,"PurchaseDate":"2015-01-11T07:00:40.363Z","ExpirationDate":"2018-11-03T06:57:53.634Z","Quantity":1},{"Name":"Garlic","Type":"Produce","Store":"7-11","Expired":false,"PurchaseDate":"2016-02-17T09:59:58.235Z","ExpirationDate":"2019-04-23T06:56:28.958Z","Quantity":7},{"Name":"Basil","Type":"Produce","Store":"Albertsons","Expired":false,"PurchaseDate":"2016-10-15T19:30:54.191Z","ExpirationDate":"2019-09-02T01:10:32.616Z","Quantity":4},{"Name":"Fish","Type":"Meat","Store":"Metropolitan Market","Expired":false,"PurchaseDate":"2018-03-28T12:48:01.064Z","ExpirationDate":"2018-06-10T22:16:13.285Z","Quantity":8},{"Name":"Cucumbers","Type":"Produce","Store":"7-11","Expired":false,"PurchaseDate":"2018-04-16T22:29:04.623Z","ExpirationDate":"2018-07-26T00:43:47.318Z","Quantity":9},{"Name":"Watercress","Type":"Produce","Store":"7-11","Expired":true,"PurchaseDate":"2017-06-07T18:11:03.13Z","ExpirationDate":"2017-01-07T08:44:29.49Z","Quantity":7},{"Name":"Radish","Type":"Produce","Store":"Safeway","Expired":false,"PurchaseDate":"2015-04-10T13:23:16.379Z","ExpirationDate":"2017-07-21T15:07:57.763Z","Quantity":4},{"Name":"Cabbage","Type":"Produce","Store":"Albertsons","Expired":false,"PurchaseDate":"2016-02-03T14:06:22.549Z","ExpirationDate":"2018-11-18T02:22:46.209Z","Quantity":2},{"Name":"Rutabaga","Type":"Produce","Store":"Trader Joe's","Expired":false,"PurchaseDate":"2015-01-16T03:47:32.208Z","ExpirationDate":"2017-06-01T00:11:18.314Z","Quantity":7},{"Name":"Chard","Type":"Produce","Store":"Safeway","Expired":false,"PurchaseDate":"2015-11-29T05:47:10.55Z","ExpirationDate":"2019-10-10T15:37:48.335Z","Quantity":1},{"Name":"Carrots","Type":"Produce","Store":"QFC","Expired":false,"PurchaseDate":"2015-08-13T19:52:03.152Z","ExpirationDate":"2018-06-06T03:45:53.771Z","Quantity":4},{"Name":"Chard","Type":"Produce","Store":"Safeway","Expired":false,"PurchaseDate":"2016-10-03T09:02:27.89Z","ExpirationDate":"2018-03-31T12:09:37.038Z","Quantity":1},{"Name":"Radish","Type":"Produce","Store":"Trader Joe's","Expired":false,"PurchaseDate":"2016-08-07T22:31:16.835Z","ExpirationDate":"2018-12-13T00:43:29.476Z","Quantity":4},{"Name":"Fish","Type":"Meat","Store":"Grocery Outlet","Expired":false,"PurchaseDate":"2017-04-05T05:10:25.064Z","ExpirationDate":"2018-01-25T11:52:33.194Z","Quantity":5},{"Name":"Butter","Type":"Dairy","Store":"Albertsons","Expired":false,"PurchaseDate":"2018-05-10T19:13:27.731Z","ExpirationDate":"2019-03-19T17:50:03.983Z","Quantity":1},{"Name":"Arugula","Type":"Produce","Store":"7-11","Expired":false,"PurchaseDate":"2015-01-26T14:30:40.937Z","ExpirationDate":"2017-07-07T05:30:02.868Z","Quantity":6},{"Name":"Chard","Type":"Produce","Store":"7-11","Expired":false,"PurchaseDate":"2016-07-20T17:49:25.139Z","ExpirationDate":"2019-07-10T00:53:44.204Z","Quantity":7},{"Name":"Green onions","Type":"Produce","Store":"7-11","Expired":false,"PurchaseDate":"2015-07-08T22:32:56.426Z","ExpirationDate":"2018-04-26T19:30:23.337Z","Quantity":6},{"Name":"Radish","Type":"Produce","Store":"7-11","Expired":false,"PurchaseDate":"2017-06-30T12:48:27.092Z","ExpirationDate":"2018-07-13T04:42:01.739Z","Quantity":6},{"Name":"Peppers","Type":"Produce","Store":"Albertsons","Expired":false,"PurchaseDate":"2016-04-17T01:36:43.033Z","ExpirationDate":"2018-05-31T11:02:06.596Z","Quantity":7},{"Name":"Asparagus","Type":"Produce","Store":"QFC","Expired":false,"PurchaseDate":"2017-10-05T02:04:08.492Z","ExpirationDate":"2018-01-19T08:15:00.697Z","Quantity":5},{"Name":"Peppers","Type":"Produce","Store":"Trader Joe's","Expired":false,"PurchaseDate":"2017-02-15T13:59:59.466Z","ExpirationDate":"2018-04-12T08:20:53.485Z","Quantity":3},{"Name":"Cabbage","Type":"Produce","Store":"Albertsons","Expired":true,"PurchaseDate":"2017-06-21T17:56:59.466Z","ExpirationDate":"2017-03-11T02:16:44.112Z","Quantity":8},{"Name":"Watermelon","Type":"Produce","Store":"7-11","Expired":false,"PurchaseDate":"2016-11-25T11:24:39.572Z","ExpirationDate":"2019-08-13T13:57:08.802Z","Quantity":3},{"Name":"Onions","Type":"Produce","Store":"Trader Joe's","Expired":false,"PurchaseDate":"2016-04-16T07:20:46.406Z","ExpirationDate":"2018-02-12T03:16:38.382Z","Quantity":4},{"Name":"Asparagus","Type":"Produce","Store":"Grocery Outlet","Expired":false,"PurchaseDate":"2016-04-19T17:27:03.428Z","ExpirationDate":"2017-05-19T06:36:20.121Z","Quantity":2},{"Name":"Arugula","Type":"Produce","Store":"Metropolitan Market","Expired":false,"PurchaseDate":"2015-02-25T18:56:40.149Z","ExpirationDate":"2019-06-30T19:45:12.844Z","Quantity":2},{"Name":"Arugula","Type":"Produce","Store":"Metropolitan Market","Expired":true,"PurchaseDate":"2018-08-14T11:24:07.981Z","ExpirationDate":"2017-11-11T19:47:30.945Z","Quantity":9},{"Name":"Arugula","Type":"Produce","Store":"Grocery Outlet","Expired":false,"PurchaseDate":"2015-01-01T23:13:47.775Z","ExpirationDate":"2019-03-09T18:41:46.82Z","Quantity":8},{"Name":"Cabbage","Type":"Produce","Store":"QFC","Expired":false,"PurchaseDate":"2016-03-03T06:19:01.236Z","ExpirationDate":"2019-06-15T13:26:36.089Z","Quantity":10},{"Name":"Cauliflower","Type":"Produce","Store":"Trader Joe's","Expired":false,"PurchaseDate":"2016-06-17T19:58:15.407Z","ExpirationDate":"2018-09-03T09:34:21.2Z","Quantity":10},{"Name":"Rutabaga","Type":"Produce","Store":"Trader Joe's","Expired":true,"PurchaseDate":"2017-10-15T10:43:26.661Z","ExpirationDate":"2017-10-12T00:24:40.832Z","Quantity":6},{"Name":"Okra","Type":"Produce","Store":"Albertsons","Expired":false,"PurchaseDate":"2017-12-04T15:56:13.105Z","ExpirationDate":"2018-07-31T23:25:44.734Z","Quantity":3},{"Name":"Peas","Type":"Produce","Store":"QFC","Expired":false,"PurchaseDate":"2016-07-27T06:34:24.406Z","ExpirationDate":"2018-07-14T15:39:45.981Z","Quantity":3},{"Name":"Broccoli","Type":"Produce","Store":"QFC","Expired":false,"PurchaseDate":"2015-01-20T16:15:14.886Z","ExpirationDate":"2018-04-23T20:38:31.864Z","Quantity":1},{"Name":"Tomatoes","Type":"Produce","Store":"Metropolitan Market","Expired":false,"PurchaseDate":"2017-02-07T11:29:11.332Z","ExpirationDate":"2018-10-02T07:33:08.922Z","Quantity":10},{"Name":"Cucumbers","Type":"Produce","Store":"Safeway","Expired":false,"PurchaseDate":"2016-07-25T08:48:24.533Z","ExpirationDate":"2017-06-19T06:38:41.753Z","Quantity":3},{"Name":"Pork","Type":"Meat","Store":"Safeway","Expired":false,"PurchaseDate":"2016-05-27T16:05:43.083Z","ExpirationDate":"2018-10-08T20:17:53.194Z","Quantity":8},{"Name":"Rutabaga","Type":"Produce","Store":"Grocery Outlet","Expired":false,"PurchaseDate":"2015-04-08T17:55:36.568Z","ExpirationDate":"2017-02-03T23:43:11.414Z","Quantity":8},{"Name":"Pork","Type":"Meat","Store":"QFC","Expired":false,"PurchaseDate":"2015-08-27T20:20:46.742Z","ExpirationDate":"2019-07-02T22:56:12.207Z","Quantity":10},{"Name":"Peas","Type":"Produce","Store":"QFC","Expired":false,"PurchaseDate":"2015-09-26T15:17:57.592Z","ExpirationDate":"2018-09-14T01:39:00.971Z","Quantity":7},{"Name":"Cabbage","Type":"Produce","Store":"QFC","Expired":true,"PurchaseDate":"2017-11-20T23:28:41.717Z","ExpirationDate":"2017-06-04T20:20:26.612Z","Quantity":3},{"Name":"Turnips","Type":"Produce","Store":"Grocery Outlet","Expired":false,"PurchaseDate":"2016-08-19T20:46:02.818Z","ExpirationDate":"2019-12-16T05:46:40.108Z","Quantity":8},{"Name":"Green onions","Type":"Produce","Store":"Metropolitan Market","Expired":true,"PurchaseDate":"2018-06-22T10:21:43.627Z","ExpirationDate":"2018-03-31T08:16:44.884Z","Quantity":9},{"Name":"Ice cream","Type":"Dairy","Store":"Metropolitan Market","Expired":false,"PurchaseDate":"2017-07-23T07:53:44.712Z","ExpirationDate":"2019-02-21T14:13:17.024Z","Quantity":8},{"Name":"Zucchini","Type":"Produce","Store":"Safeway","Expired":false,"PurchaseDate":"2015-08-06T03:54:08.902Z","ExpirationDate":"2017-08-24T11:32:36.409Z","Quantity":10},{"Name":"Potatoes","Type":"Produce","Store":"QFC","Expired":false,"PurchaseDate":"2017-05-03T19:03:44.505Z","ExpirationDate":"2018-12-08T04:34:31.562Z","Quantity":1},{"Name":"Lamb","Type":"Meat","Store":"Metropolitan Market","Expired":false,"PurchaseDate":"2015-10-25T05:22:27.296Z","ExpirationDate":"2017-10-08T19:48:40.135Z","Quantity":4},{"Name":"Cabbage","Type":"Produce","Store":"Metropolitan Market","Expired":false,"PurchaseDate":"2017-07-17T02:48:54.135Z","ExpirationDate":"2019-12-23T20:44:06.356Z","Quantity":4},{"Name":"Butter","Type":"Dairy","Store":"QFC","Expired":false,"PurchaseDate":"2017-08-15T04:39:44.98Z","ExpirationDate":"2019-12-09T22:41:33.916Z","Quantity":3},{"Name":"Chicken","Type":"Meat","Store":"Metropolitan Market","Expired":false,"PurchaseDate":"2015-06-30T12:41:03.699Z","ExpirationDate":"2018-04-03T18:13:01.523Z","Quantity":3},{"Name":"Cabbage","Type":"Produce","Store":"QFC","Expired":false,"PurchaseDate":"2015-02-08T12:52:31.191Z","ExpirationDate":"2017-03-31T13:21:55.712Z","Quantity":10},{"Name":"Eggplant","Type":"Produce","Store":"Metropolitan Market","Expired":false,"PurchaseDate":"2015-04-27T08:23:51.774Z","ExpirationDate":"2018-11-19T00:17:27.684Z","Quantity":10},{"Name":"Watercress","Type":"Produce","Store":"Grocery Outlet","Expired":true,"PurchaseDate":"2017-10-20T00:15:02.276Z","ExpirationDate":"2017-05-07T13:28:59.218Z","Quantity":7},{"Name":"Lettuce","Type":"Produce","Store":"Safeway","Expired":false,"PurchaseDate":"2017-08-08T05:07:52.274Z","ExpirationDate":"2017-10-18T19:39:08.47Z","Quantity":8},{"Name":"Fennel","Type":"Produce","Store":"Metropolitan Market","Expired":true,"PurchaseDate":"2017-12-30T12:27:59.145Z","ExpirationDate":"2017-10-20T22:26:58.071Z","Quantity":9},{"Name":"Radish","Type":"Produce","Store":"7-11","Expired":false,"PurchaseDate":"2016-07-23T20:28:32.93Z","ExpirationDate":"2019-08-12T05:37:58.682Z","Quantity":6},{"Name":"Cucumbers","Type":"Produce","Store":"Grocery Outlet","Expired":false,"PurchaseDate":"2016-03-18T03:35:21.563Z","ExpirationDate":"2019-04-27T20:14:56.599Z","Quantity":10},{"Name":"Lettuce","Type":"Produce","Store":"Trader Joe's","Expired":false,"PurchaseDate":"2017-11-08T08:52:01.434Z","ExpirationDate":"2019-06-20T19:27:04.478Z","Quantity":9},{"Name":"Peppers","Type":"Produce","Store":"QFC","Expired":false,"PurchaseDate":"2015-09-02T16:57:02.203Z","ExpirationDate":"2017-06-09T18:31:42.887Z","Quantity":8},{"Name":"Lettuce","Type":"Produce","Store":"Grocery Outlet","Expired":false,"PurchaseDate":"2018-01-26T12:57:33.017Z","ExpirationDate":"2019-09-18T03:12:50.262Z","Quantity":2},{"Name":"Asparagus","Type":"Produce","Store":"Trader Joe's","Expired":false,"PurchaseDate":"2015-03-30T17:08:41.376Z","ExpirationDate":"2018-04-08T03:30:38.126Z","Quantity":3},{"Name":"Beef","Type":"Meat","Store":"Metropolitan Market","Expired":false,"PurchaseDate":"2016-12-15T16:30:17.56Z","ExpirationDate":"2018-03-28T05:52:13.788Z","Quantity":6},{"Name":"Chicken","Type":"Meat","Store":"7-11","Expired":false,"PurchaseDate":"2017-08-12T19:44:33.776Z","ExpirationDate":"2017-08-31T19:29:36.048Z","Quantity":10},{"Name":"Carrots","Type":"Produce","Store":"Trader Joe's","Expired":false,"PurchaseDate":"2015-07-19T07:31:27.943Z","ExpirationDate":"2017-09-04T22:11:58.456Z","Quantity":7},{"Name":"Chicken","Type":"Meat","Store":"Trader Joe's","Expired":false,"PurchaseDate":"2017-02-10T01:54:23.181Z","ExpirationDate":"2019-08-22T01:37:35.948Z","Quantity":2},{"Name":"Zucchini","Type":"Produce","Store":"Metropolitan Market","Expired":false,"PurchaseDate":"2016-02-01T09:34:47.483Z","ExpirationDate":"2018-10-25T03:06:15.614Z","Quantity":7},{"Name":"Watercress","Type":"Produce","Store":"Albertsons","Expired":false,"PurchaseDate":"2016-04-06T15:29:12.096Z","ExpirationDate":"2018-11-23T01:54:01.184Z","Quantity":10},{"Name":"Cucumbers","Type":"Produce","Store":"Safeway","Expired":false,"PurchaseDate":"2016-07-08T17:14:04.992Z","ExpirationDate":"2019-05-17T12:04:58.519Z","Quantity":4},{"Name":"Ice cream","Type":"Dairy","Store":"Grocery Outlet","Expired":false,"PurchaseDate":"2016-04-25T09:51:52.937Z","ExpirationDate":"2017-06-29T06:26:23.271Z","Quantity":1},{"Name":"Ice cream","Type":"Dairy","Store":"Metropolitan Market","Expired":false,"PurchaseDate":"2016-08-17T20:43:46.057Z","ExpirationDate":"2018-07-22T10:33:43.385Z","Quantity":9},{"Name":"Cabbage","Type":"Produce","Store":"7-11","Expired":false,"PurchaseDate":"2018-06-27T18:57:44.089Z","ExpirationDate":"2019-08-02T04:01:14.558Z","Quantity":7},{"Name":"Green onions","Type":"Produce","Store":"Safeway","Expired":false,"PurchaseDate":"2017-01-29T10:02:29.22Z","ExpirationDate":"2018-10-02T00:56:17.765Z","Quantity":9},{"Name":"Potatoes","Type":"Produce","Store":"Metropolitan Market","Expired":false,"PurchaseDate":"2015-10-31T10:14:01.819Z","ExpirationDate":"2017-09-05T10:25:54.333Z","Quantity":6},{"Name":"Basil","Type":"Produce","Store":"Metropolitan Market","Expired":false,"PurchaseDate":"2018-01-16T12:00:37.675Z","ExpirationDate":"2019-01-23T05:50:17.163Z","Quantity":2},{"Name":"Beef","Type":"Meat","Store":"Trader Joe's","Expired":true,"PurchaseDate":"2018-07-15T15:00:44.228Z","ExpirationDate":"2018-02-22T20:34:02.301Z","Quantity":7},{"Name":"Lamb","Type":"Meat","Store":"7-11","Expired":false,"PurchaseDate":"2016-01-26T20:06:32.023Z","ExpirationDate":"2019-06-27T15:12:35.537Z","Quantity":2},{"Name":"Ice cream","Type":"Dairy","Store":"Safeway","Expired":false,"PurchaseDate":"2016-04-28T02:21:20.501Z","ExpirationDate":"2018-02-20T04:07:48.679Z","Quantity":7},{"Name":"Fish","Type":"Meat","Store":"Metropolitan Market","Expired":false,"PurchaseDate":"2016-05-13T07:52:11.168Z","ExpirationDate":"2018-02-08T21:37:00.413Z","Quantity":7},{"Name":"Arugula","Type":"Produce","Store":"Metropolitan Market","Expired":false,"PurchaseDate":"2017-04-12T22:18:15.933Z","ExpirationDate":"2018-02-26T23:11:56.001Z","Quantity":4},{"Name":"Zucchini","Type":"Produce","Store":"Albertsons","Expired":false,"PurchaseDate":"2016-04-20T18:02:37.005Z","ExpirationDate":"2017-07-01T19:11:52.415Z","Quantity":4},{"Name":"Milk","Type":"Dairy","Store":"7-11","Expired":false,"PurchaseDate":"2017-01-17T04:08:14.335Z","ExpirationDate":"2019-08-09T21:35:23.622Z","Quantity":1},{"Name":"Cauliflower","Type":"Produce","Store":"Safeway","Expired":false,"PurchaseDate":"2018-01-17T09:28:15.696Z","ExpirationDate":"2019-10-16T14:59:17.682Z","Quantity":5},{"Name":"Tomatoes","Type":"Produce","Store":"Albertsons","Expired":false,"PurchaseDate":"2017-02-06T19:30:15.566Z","ExpirationDate":"2017-03-23T21:58:55.425Z","Quantity":1},{"Name":"Chard","Type":"Produce","Store":"QFC","Expired":false,"PurchaseDate":"2016-06-23T13:29:18.305Z","ExpirationDate":"2017-06-01T03:36:52.382Z","Quantity":3},{"Name":"Broccoli","Type":"Produce","Store":"Safeway","Expired":false,"PurchaseDate":"2016-12-02T04:16:27.656Z","ExpirationDate":"2019-03-12T16:17:30.336Z","Quantity":1},{"Name":"Basil","Type":"Produce","Store":"Metropolitan Market","Expired":false,"PurchaseDate":"2017-04-18T02:56:55.091Z","ExpirationDate":"2019-05-09T18:26:45.614Z","Quantity":9},{"Name":"Garlic","Type":"Produce","Store":"QFC","Expired":false,"PurchaseDate":"2018-03-13T12:12:56.731Z","ExpirationDate":"2018-05-27T16:53:44.921Z","Quantity":9},{"Name":"Fennel","Type":"Produce","Store":"Safeway","Expired":false,"PurchaseDate":"2016-03-19T02:41:42.721Z","ExpirationDate":"2019-11-20T09:20:07.966Z","Quantity":8},{"Name":"Spinach","Type":"Produce","Store":"QFC","Expired":false,"PurchaseDate":"2017-01-05T23:17:17.096Z","ExpirationDate":"2019-02-21T16:24:02.354Z","Quantity":7},{"Name":"Lettuce","Type":"Produce","Store":"7-11","Expired":true,"PurchaseDate":"2018-01-23T23:13:02.7Z","ExpirationDate":"2017-10-13T10:32:15.618Z","Quantity":5},{"Name":"Potatoes","Type":"Produce","Store":"Metropolitan Market","Expired":true,"PurchaseDate":"2017-09-24T17:05:07.535Z","ExpirationDate":"2017-04-24T17:54:42.061Z","Quantity":6},{"Name":"Asparagus","Type":"Produce","Store":"Albertsons","Expired":false,"PurchaseDate":"2017-02-23T23:23:20.453Z","ExpirationDate":"2019-04-28T07:39:24.606Z","Quantity":6},{"Name":"Radish","Type":"Produce","Store":"Safeway","Expired":false,"PurchaseDate":"2016-06-08T05:41:57.864Z","ExpirationDate":"2018-07-06T01:47:03.99Z","Quantity":10},{"Name":"Tomatoes","Type":"Produce","Store":"Safeway","Expired":false,"PurchaseDate":"2018-01-22T15:12:32.557Z","ExpirationDate":"2018-09-18T10:19:44.196Z","Quantity":1},{"Name":"Cheese","Type":"Dairy","Store":"7-11","Expired":false,"PurchaseDate":"2015-11-03T22:59:48.078Z","ExpirationDate":"2019-11-03T12:15:12.513Z","Quantity":2},{"Name":"Potatoes","Type":"Produce","Store":"Albertsons","Expired":false,"PurchaseDate":"2016-01-30T10:47:04.346Z","ExpirationDate":"2019-09-01T18:42:51.545Z","Quantity":1},{"Name":"Green onions","Type":"Produce","Store":"Metropolitan Market","Expired":false,"PurchaseDate":"2016-09-14T03:17:29.692Z","ExpirationDate":"2019-06-19T14:38:22.024Z","Quantity":6},{"Name":"Garlic","Type":"Produce","Store":"QFC","Expired":false,"PurchaseDate":"2017-03-17T22:24:07.147Z","ExpirationDate":"2019-12-02T15:31:26.329Z","Quantity":5},{"Name":"Milk","Type":"Dairy","Store":"QFC","Expired":false,"PurchaseDate":"2017-06-17T08:24:08.539Z","ExpirationDate":"2018-02-17T20:20:56.778Z","Quantity":4},{"Name":"Onions","Type":"Produce","Store":"7-11","Expired":true,"PurchaseDate":"2017-10-25T23:26:03.877Z","ExpirationDate":"2017-08-26T08:33:09.986Z","Quantity":6},{"Name":"Broccoli","Type":"Produce","Store":"Trader Joe's","Expired":false,"PurchaseDate":"2016-05-13T19:07:37.645Z","ExpirationDate":"2019-02-13T06:36:17.712Z","Quantity":4},{"Name":"Basil","Type":"Produce","Store":"7-11","Expired":false,"PurchaseDate":"2015-11-10T12:13:33.769Z","ExpirationDate":"2018-07-03T05:06:28.826Z","Quantity":8},{"Name":"Onions","Type":"Produce","Store":"QFC","Expired":false,"PurchaseDate":"2017-11-11T10:00:45.852Z","ExpirationDate":"2018-12-27T04:15:01.326Z","Quantity":2},{"Name":"Asparagus","Type":"Produce","Store":"Albertsons","Expired":false,"PurchaseDate":"2017-01-22T09:27:39.076Z","ExpirationDate":"2017-03-27T22:00:24.204Z","Quantity":5},{"Name":"Broccoli","Type":"Produce","Store":"7-11","Expired":false,"PurchaseDate":"2015-03-03T12:09:26.373Z","ExpirationDate":"2019-06-23T04:15:12.047Z","Quantity":8},{"Name":"Zucchini","Type":"Produce","Store":"Albertsons","Expired":false,"PurchaseDate":"2017-05-12T11:27:31.544Z","ExpirationDate":"2019-04-01T13:20:01.817Z","Quantity":8},{"Name":"Peppers","Type":"Produce","Store":"7-11","Expired":true,"PurchaseDate":"2018-01-10T17:38:40.315Z","ExpirationDate":"2017-04-17T06:59:25.578Z","Quantity":4},{"Name":"Watermelon","Type":"Produce","Store":"Metropolitan Market","Expired":false,"PurchaseDate":"2017-09-14T20:50:21.458Z","ExpirationDate":"2017-10-17T07:30:34.592Z","Quantity":4},{"Name":"Lettuce","Type":"Produce","Store":"Trader Joe's","Expired":false,"PurchaseDate":"2016-11-25T00:56:37.578Z","ExpirationDate":"2018-03-15T09:49:20.643Z","Quantity":2},{"Name":"Cheese","Type":"Dairy","Store":"Albertsons","Expired":false,"PurchaseDate":"2015-06-09T04:13:14.893Z","ExpirationDate":"2018-09-01T12:22:38.718Z","Quantity":7},{"Name":"Watermelon","Type":"Produce","Store":"QFC","Expired":false,"PurchaseDate":"2015-06-30T08:55:08.532Z","ExpirationDate":"2017-09-02T06:53:30.269Z","Quantity":7},{"Name":"Cucumbers","Type":"Produce","Store":"Metropolitan Market","Expired":false,"PurchaseDate":"2017-07-14T04:29:37.237Z","ExpirationDate":"2019-10-04T10:56:02.225Z","Quantity":2},{"Name":"Tomatoes","Type":"Produce","Store":"Albertsons","Expired":false,"PurchaseDate":"2017-04-02T16:50:20.707Z","ExpirationDate":"2018-12-31T09:50:39.606Z","Quantity":2},{"Name":"Rutabaga","Type":"Produce","Store":"7-11","Expired":false,"PurchaseDate":"2015-09-28T02:22:06.205Z","ExpirationDate":"2018-03-15T05:07:00.88Z","Quantity":4},{"Name":"Zucchini","Type":"Produce","Store":"Albertsons","Expired":false,"PurchaseDate":"2018-06-07T18:59:50.002Z","ExpirationDate":"2018-06-13T15:03:07.5Z","Quantity":2},{"Name":"Tomatoes","Type":"Produce","Store":"Trader Joe's","Expired":false,"PurchaseDate":"2018-02-11T13:32:44.036Z","ExpirationDate":"2019-01-12T15:53:57.868Z","Quantity":8},{"Name":"Radish","Type":"Produce","Store":"Safeway","Expired":false,"PurchaseDate":"2017-03-26T20:32:33.655Z","ExpirationDate":"2018-08-11T22:55:30.039Z","Quantity":7},{"Name":"Pork","Type":"Meat","Store":"Trader Joe's","Expired":false,"PurchaseDate":"2017-03-22T22:43:00.577Z","ExpirationDate":"2017-09-20T20:32:15.573Z","Quantity":6},{"Name":"Yoghurt","Type":"Dairy","Store":"Trader Joe's","Expired":false,"PurchaseDate":"2018-05-02T22:47:50.505Z","ExpirationDate":"2019-05-27T01:36:40.822Z","Quantity":4},{"Name":"Rutabaga","Type":"Produce","Store":"Grocery Outlet","Expired":true,"PurchaseDate":"2017-10-15T15:29:35.901Z","ExpirationDate":"2017-05-29T10:25:05.31Z","Quantity":4},{"Name":"Cheese","Type":"Dairy","Store":"Grocery Outlet","Expired":true,"PurchaseDate":"2017-05-26T18:14:08.062Z","ExpirationDate":"2017-04-17T02:03:12.051Z","Quantity":2},{"Name":"Pork","Type":"Meat","Store":"Grocery Outlet","Expired":false,"PurchaseDate":"2017-03-21T04:31:41.844Z","ExpirationDate":"2019-10-01T16:00:00.663Z","Quantity":9},{"Name":"Watercress","Type":"Produce","Store":"Metropolitan Market","Expired":false,"PurchaseDate":"2017-03-17T00:51:02.421Z","ExpirationDate":"2019-08-18T17:23:42.186Z","Quantity":9},{"Name":"Green onions","Type":"Produce","Store":"Grocery Outlet","Expired":false,"PurchaseDate":"2015-05-28T23:02:48.453Z","ExpirationDate":"2018-03-10T16:18:10.671Z","Quantity":10},{"Name":"Rhubarb","Type":"Produce","Store":"QFC","Expired":false,"PurchaseDate":"2017-11-30T09:15:28.77Z","ExpirationDate":"2018-11-13T09:59:32.142Z","Quantity":10},{"Name":"Rutabaga","Type":"Produce","Store":"Safeway","Expired":false,"PurchaseDate":"2017-08-24T10:21:38.413Z","ExpirationDate":"2018-04-18T15:15:32.068Z","Quantity":2},{"Name":"Asparagus","Type":"Produce","Store":"Trader Joe's","Expired":false,"PurchaseDate":"2016-01-26T09:40:15.655Z","ExpirationDate":"2017-11-04T04:57:02.314Z","Quantity":4},{"Name":"Peas","Type":"Produce","Store":"Metropolitan Market","Expired":false,"PurchaseDate":"2015-11-09T22:21:25.828Z","ExpirationDate":"2017-11-22T08:18:27.223Z","Quantity":10},{"Name":"Watercress","Type":"Produce","Store":"Grocery Outlet","Expired":false,"PurchaseDate":"2017-01-11T07:32:44.28Z","ExpirationDate":"2017-11-11T01:37:25.471Z","Quantity":10},{"Name":"Chard","Type":"Produce","Store":"Safeway","Expired":false,"PurchaseDate":"2015-06-11T02:09:33.004Z","ExpirationDate":"2019-08-29T19:04:26.854Z","Quantity":5},{"Name":"Broccoli","Type":"Produce","Store":"Safeway","Expired":false,"PurchaseDate":"2018-05-09T17:31:57.494Z","ExpirationDate":"2019-02-01T16:23:36.496Z","Quantity":7},{"Name":"Chard","Type":"Produce","Store":"Metropolitan Market","Expired":false,"PurchaseDate":"2017-02-09T10:24:26.069Z","ExpirationDate":"2018-03-05T15:54:41.054Z","Quantity":1},{"Name":"Cauliflower","Type":"Produce","Store":"Safeway","Expired":true,"PurchaseDate":"2018-07-23T09:52:40.316Z","ExpirationDate":"2017-09-16T21:13:27.13Z","Quantity":3},{"Name":"Cucumbers","Type":"Produce","Store":"Safeway","Expired":true,"PurchaseDate":"2017-08-18T18:00:29.614Z","ExpirationDate":"2017-02-10T17:43:33.798Z","Quantity":6},{"Name":"Arugula","Type":"Produce","Store":"Safeway","Expired":true,"PurchaseDate":"2018-03-16T11:55:05.695Z","ExpirationDate":"2017-11-17T09:05:18.861Z","Quantity":7},{"Name":"Carrots","Type":"Produce","Store":"Metropolitan Market","Expired":true,"PurchaseDate":"2018-06-02T14:56:03.367Z","ExpirationDate":"2018-03-04T10:35:21.108Z","Quantity":7},{"Name":"Fish","Type":"Meat","Store":"Trader Joe's","Expired":true,"PurchaseDate":"2017-10-01T01:56:37.226Z","ExpirationDate":"2017-04-24T08:06:29.105Z","Quantity":6},{"Name":"Fennel","Type":"Produce","Store":"Safeway","Expired":false,"PurchaseDate":"2016-09-17T04:01:06.52Z","ExpirationDate":"2018-08-29T14:17:02.153Z","Quantity":7},{"Name":"Tomatoes","Type":"Produce","Store":"7-11","Expired":false,"PurchaseDate":"2016-02-26T00:17:47.821Z","ExpirationDate":"2018-01-07T13:36:14.949Z","Quantity":9},{"Name":"Asparagus","Type":"Produce","Store":"Grocery Outlet","Expired":false,"PurchaseDate":"2018-07-18T22:18:19.383Z","ExpirationDate":"2018-12-10T02:10:19.279Z","Quantity":5},{"Name":"Green onions","Type":"Produce","Store":"Grocery Outlet","Expired":false,"PurchaseDate":"2017-01-22T10:06:59.822Z","ExpirationDate":"2017-10-03T10:52:46.606Z","Quantity":10},{"Name":"Fennel","Type":"Produce","Store":"Metropolitan Market","Expired":false,"PurchaseDate":"2016-06-01T08:25:01.808Z","ExpirationDate":"2019-03-14T04:26:57.054Z","Quantity":4},{"Name":"Spinach","Type":"Produce","Store":"Trader Joe's","Expired":false,"PurchaseDate":"2017-07-02T11:18:35.447Z","ExpirationDate":"2018-06-14T15:10:30.279Z","Quantity":1},{"Name":"Peppers","Type":"Produce","Store":"Metropolitan Market","Expired":false,"PurchaseDate":"2016-06-01T06:32:29.649Z","ExpirationDate":"2017-02-21T02:51:22.957Z","Quantity":8},{"Name":"Watercress","Type":"Produce","Store":"Trader Joe's","Expired":false,"PurchaseDate":"2018-05-02T05:04:07.597Z","ExpirationDate":"2019-12-08T16:42:11.842Z","Quantity":10},{"Name":"Peas","Type":"Produce","Store":"Trader Joe's","Expired":false,"PurchaseDate":"2015-09-10T21:02:01.778Z","ExpirationDate":"2017-12-23T05:11:19.313Z","Quantity":6},{"Name":"Broccoli","Type":"Produce","Store":"Safeway","Expired":false,"PurchaseDate":"2016-03-08T04:32:14.508Z","ExpirationDate":"2017-03-18T15:37:14.377Z","Quantity":1},{"Name":"Okra","Type":"Produce","Store":"Trader Joe's","Expired":false,"PurchaseDate":"2015-02-19T05:49:35.308Z","ExpirationDate":"2018-06-14T03:45:57.793Z","Quantity":10},{"Name":"Cabbage","Type":"Produce","Store":"7-11","Expired":false,"PurchaseDate":"2017-09-07T10:01:05.785Z","ExpirationDate":"2019-02-27T17:18:49.563Z","Quantity":8},{"Name":"Okra","Type":"Produce","Store":"Albertsons","Expired":false,"PurchaseDate":"2016-05-08T19:47:25.022Z","ExpirationDate":"2018-03-28T10:57:21.065Z","Quantity":7},{"Name":"Cheese","Type":"Dairy","Store":"Safeway","Expired":false,"PurchaseDate":"2017-01-02T18:39:47.552Z","ExpirationDate":"2017-07-27T10:38:26.725Z","Quantity":5},{"Name":"Potatoes","Type":"Produce","Store":"Grocery Outlet","Expired":false,"PurchaseDate":"2018-02-24T17:49:22.236Z","ExpirationDate":"2018-12-18T18:45:42.112Z","Quantity":2},{"Name":"Chicken","Type":"Meat","Store":"Trader Joe's","Expired":true,"PurchaseDate":"2018-01-03T01:35:40.033Z","ExpirationDate":"2017-06-10T09:59:59.843Z","Quantity":1},{"Name":"Milk","Type":"Dairy","Store":"Trader Joe's","Expired":false,"PurchaseDate":"2015-05-29T18:40:27.6Z","ExpirationDate":"2019-11-06T23:55:06.295Z","Quantity":7},{"Name":"Fish","Type":"Meat","Store":"Safeway","Expired":false,"PurchaseDate":"2015-11-14T14:31:56.108Z","ExpirationDate":"2017-06-19T20:03:08.539Z","Quantity":3},{"Name":"Eggplant","Type":"Produce","Store":"Trader Joe's","Expired":false,"PurchaseDate":"2018-06-22T21:59:41.116Z","ExpirationDate":"2019-10-12T01:26:08.376Z","Quantity":6},{"Name":"Rhubarb","Type":"Produce","Store":"Trader Joe's","Expired":false,"PurchaseDate":"2016-02-10T13:27:03.304Z","ExpirationDate":"2018-01-12T05:09:20.844Z","Quantity":3},{"Name":"Ice cream","Type":"Dairy","Store":"QFC","Expired":false,"PurchaseDate":"2016-12-28T05:35:40.345Z","ExpirationDate":"2019-12-24T08:50:37.453Z","Quantity":7},{"Name":"Cauliflower","Type":"Produce","Store":"Safeway","Expired":false,"PurchaseDate":"2017-01-28T12:16:21.566Z","ExpirationDate":"2019-10-27T01:05:21.2Z","Quantity":1},{"Name":"Potatoes","Type":"Produce","Store":"Metropolitan Market","Expired":false,"PurchaseDate":"2016-04-14T15:52:03.842Z","ExpirationDate":"2017-06-21T02:29:10.725Z","Quantity":10},{"Name":"Lamb","Type":"Meat","Store":"Albertsons","Expired":true,"PurchaseDate":"2017-10-09T14:53:34.101Z","ExpirationDate":"2017-09-28T10:09:52.445Z","Quantity":9},{"Name":"Green onions","Type":"Produce","Store":"7-11","Expired":false,"PurchaseDate":"2016-09-10T16:07:20.172Z","ExpirationDate":"2019-08-30T23:31:25.072Z","Quantity":3},{"Name":"Peppers","Type":"Produce","Store":"Grocery Outlet","Expired":false,"PurchaseDate":"2016-04-10T23:53:01.579Z","ExpirationDate":"2019-02-03T10:50:09.181Z","Quantity":8},{"Name":"Green onions","Type":"Produce","Store":"QFC","Expired":false,"PurchaseDate":"2018-01-09T01:52:37.965Z","ExpirationDate":"2019-07-10T15:30:58.09Z","Quantity":10},{"Name":"Peas","Type":"Produce","Store":"Safeway","Expired":true,"PurchaseDate":"2018-04-22T21:58:11.782Z","ExpirationDate":"2018-01-17T19:01:13.191Z","Quantity":3},{"Name":"Watermelon","Type":"Produce","Store":"7-11","Expired":false,"PurchaseDate":"2016-01-13T18:45:58.562Z","ExpirationDate":"2017-07-11T10:03:33.41Z","Quantity":2},{"Name":"Fennel","Type":"Produce","Store":"QFC","Expired":false,"PurchaseDate":"2016-10-22T07:44:18.869Z","ExpirationDate":"2017-08-19T17:14:23.148Z","Quantity":4},{"Name":"Ice cream","Type":"Dairy","Store":"7-11","Expired":false,"PurchaseDate":"2016-04-04T02:18:29.242Z","ExpirationDate":"2017-03-27T11:32:30.281Z","Quantity":8},{"Name":"Fennel","Type":"Produce","Store":"7-11","Expired":false,"PurchaseDate":"2017-03-27T12:51:23.385Z","ExpirationDate":"2018-09-15T17:47:01.516Z","Quantity":1},{"Name":"Rutabaga","Type":"Produce","Store":"7-11","Expired":false,"PurchaseDate":"2017-12-07T18:48:37.734Z","ExpirationDate":"2019-09-10T16:49:55.266Z","Quantity":9},{"Name":"Okra","Type":"Produce","Store":"Grocery Outlet","Expired":false,"PurchaseDate":"2017-08-12T22:06:12.592Z","ExpirationDate":"2018-03-26T01:51:56.278Z","Quantity":2},{"Name":"Onions","Type":"Produce","Store":"Grocery Outlet","Expired":false,"PurchaseDate":"2016-10-11T15:18:25.224Z","ExpirationDate":"2019-09-22T15:19:07.538Z","Quantity":3},{"Name":"Carrots","Type":"Produce","Store":"Metropolitan Market","Expired":false,"PurchaseDate":"2017-09-25T10:03:15.79Z","ExpirationDate":"2018-04-28T09:28:01.125Z","Quantity":9},{"Name":"Peppers","Type":"Produce","Store":"Metropolitan Market","Expired":false,"PurchaseDate":"2017-07-16T16:01:52.983Z","ExpirationDate":"2018-05-11T14:19:01.664Z","Quantity":4},{"Name":"Butter","Type":"Dairy","Store":"7-11","Expired":false,"PurchaseDate":"2017-05-16T18:49:20.478Z","ExpirationDate":"2017-12-02T01:15:58.315Z","Quantity":6},{"Name":"Rhubarb","Type":"Produce","Store":"Grocery Outlet","Expired":false,"PurchaseDate":"2017-01-21T21:34:18.236Z","ExpirationDate":"2019-06-02T06:09:25.373Z","Quantity":1},{"Name":"Peas","Type":"Produce","Store":"Metropolitan Market","Expired":false,"PurchaseDate":"2015-06-27T00:42:51.135Z","ExpirationDate":"2017-03-17T08:11:59.912Z","Quantity":7},{"Name":"Peppers","Type":"Produce","Store":"Safeway","Expired":false,"PurchaseDate":"2015-09-29T21:05:07.825Z","ExpirationDate":"2019-01-05T17:01:33.446Z","Quantity":6},{"Name":"Peas","Type":"Produce","Store":"Grocery Outlet","Expired":false,"PurchaseDate":"2016-08-31T13:37:54.929Z","ExpirationDate":"2017-03-26T17:48:04.515Z","Quantity":5},{"Name":"Peas","Type":"Produce","Store":"Grocery Outlet","Expired":false,"PurchaseDate":"2017-08-13T03:22:48.109Z","ExpirationDate":"2019-05-08T10:52:34.23Z","Quantity":5},{"Name":"Butter","Type":"Dairy","Store":"Albertsons","Expired":false,"PurchaseDate":"2015-10-24T17:49:10.27Z","ExpirationDate":"2019-05-17T21:00:20.322Z","Quantity":5},{"Name":"Spinach","Type":"Produce","Store":"Trader Joe's","Expired":false,"PurchaseDate":"2016-01-30T20:00:12.912Z","ExpirationDate":"2018-02-02T19:50:52.648Z","Quantity":5},{"Name":"Radish","Type":"Produce","Store":"Albertsons","Expired":false,"PurchaseDate":"2015-03-22T09:02:35.334Z","ExpirationDate":"2019-02-08T11:04:37.229Z","Quantity":10},{"Name":"Cabbage","Type":"Produce","Store":"QFC","Expired":false,"PurchaseDate":"2017-10-29T02:11:28.82Z","ExpirationDate":"2019-06-24T07:40:43.415Z","Quantity":7},{"Name":"Beef","Type":"Meat","Store":"Safeway","Expired":false,"PurchaseDate":"2015-10-10T13:01:20.457Z","ExpirationDate":"2018-08-18T20:16:22.452Z","Quantity":8},{"Name":"Radish","Type":"Produce","Store":"Safeway","Expired":false,"PurchaseDate":"2016-06-09T18:18:49.894Z","ExpirationDate":"2017-07-23T03:39:36.639Z","Quantity":10},{"Name":"Rutabaga","Type":"Produce","Store":"Trader Joe's","Expired":false,"PurchaseDate":"2017-01-11T14:29:17.981Z","ExpirationDate":"2019-03-21T18:40:43.396Z","Quantity":4},{"Name":"Cauliflower","Type":"Produce","Store":"Trader Joe's","Expired":false,"PurchaseDate":"2017-11-19T17:40:26.124Z","ExpirationDate":"2018-06-17T20:06:50.642Z","Quantity":8},{"Name":"Watercress","Type":"Produce","Store":"7-11","Expired":false,"PurchaseDate":"2015-01-12T07:37:01.984Z","ExpirationDate":"2018-05-10T03:34:39.596Z","Quantity":10},{"Name":"Potatoes","Type":"Produce","Store":"Metropolitan Market","Expired":false,"PurchaseDate":"2015-05-12T08:59:05.699Z","ExpirationDate":"2017-11-09T05:11:02.946Z","Quantity":1},{"Name":"Fish","Type":"Meat","Store":"7-11","Expired":false,"PurchaseDate":"2016-07-11T13:53:19.622Z","ExpirationDate":"2017-04-20T02:47:06.774Z","Quantity":7},{"Name":"Basil","Type":"Produce","Store":"Albertsons","Expired":false,"PurchaseDate":"2016-07-26T06:39:41.454Z","ExpirationDate":"2018-11-13T22:06:51.21Z","Quantity":8},{"Name":"Radish","Type":"Produce","Store":"Albertsons","Expired":false,"PurchaseDate":"2017-02-27T12:49:32.587Z","ExpirationDate":"2018-01-22T04:19:41.683Z","Quantity":7},{"Name":"Radish","Type":"Produce","Store":"Albertsons","Expired":false,"PurchaseDate":"2016-03-05T07:42:53.861Z","ExpirationDate":"2017-02-26T22:02:51.898Z","Quantity":7},{"Name":"Radish","Type":"Produce","Store":"Metropolitan Market","Expired":false,"PurchaseDate":"2016-02-20T10:32:46.164Z","ExpirationDate":"2017-05-09T21:21:24.942Z","Quantity":3}]